{
  "2026-03-14": {
    "vacancy": 260,
    "avg_price": 24600.0,
    "last_vacancy": 266,
    "last_avg_price": 24037.0,
    "vacancy_diff": -6,
    "avg_price_diff": 563.0,
    "my_price": 29600.0,
    "my_vs_avg_pct": 20.3
  },
  "2026-03-15": {
    "vacancy": 285,
    "avg_price": 13069.0,
    "last_vacancy": 290,
    "last_avg_price": 13613.0,
    "vacancy_diff": -5,
    "avg_price_diff": -544.0,
    "my_price": 17600.0,
    "my_vs_avg_pct": 34.7
  },
  "2026-03-16": {
    "vacancy": 280,
    "avg_price": 13517.0,
    "last_vacancy": 291,
    "last_avg_price": 14329.0,
    "vacancy_diff": -11,
    "avg_price_diff": -812.0,
    "my_price": 16400.0,
    "my_vs_avg_pct": 21.3
  },
  "2026-03-17": {
    "vacancy": 276,
    "avg_price": 15233.0,
    "last_vacancy": 282,
    "last_avg_price": 14464.0,
    "vacancy_diff": -6,
    "avg_price_diff": 769.0,
    "my_price": 18800.0,
    "my_vs_avg_pct": 23.4
  },
  "2026-03-18": {
    "vacancy": 281,
    "avg_price": 14651.0,
    "last_vacancy": 288,
    "last_avg_price": 14683.0,
    "vacancy_diff": -7,
    "avg_price_diff": -32.0,
    "my_price": 20000.0,
    "my_vs_avg_pct": 36.5
  },
  "2026-03-19": {
    "vacancy": 277,
    "avg_price": 15711.0,
    "last_vacancy": 282,
    "last_avg_price": 15251.0,
    "vacancy_diff": -5,
    "avg_price_diff": 460.0,
    "my_price": 21200.0,
    "my_vs_avg_pct": 34.9
  },
  "2026-03-20": {
    "vacancy": 154,
    "avg_price": 28306.0,
    "last_vacancy": 171,
    "last_avg_price": 27662.0,
    "vacancy_diff": -17,
    "avg_price_diff": 644.0,
    "my_price": 31100.0,
    "my_vs_avg_pct": 9.9
  },
  "2026-03-21": {
    "vacancy": 216,
    "avg_price": 26168.0,
    "last_vacancy": 226,
    "last_avg_price": 26483.0,
    "vacancy_diff": -10,
    "avg_price_diff": -315.0,
    "my_price": 28100.0,
    "my_vs_avg_pct": 7.4
  },
  "2026-03-22": {
    "vacancy": 294,
    "avg_price": 15427.0,
    "last_vacancy": 300,
    "last_avg_price": 15435.0,
    "vacancy_diff": -6,
    "avg_price_diff": -8.0,
    "my_price": 18000.0,
    "my_vs_avg_pct": 16.7
  },
  "2026-03-23": {
    "vacancy": 292,
    "avg_price": 15282.0,
    "last_vacancy": 296,
    "last_avg_price": 15239.0,
    "vacancy_diff": -4,
    "avg_price_diff": 43.0,
    "my_price": 15600.0,
    "my_vs_avg_pct": 2.1
  },
  "2026-03-24": {
    "vacancy": 286,
    "avg_price": 15315.0,
    "last_vacancy": 291,
    "last_avg_price": 16104.0,
    "vacancy_diff": -5,
    "avg_price_diff": -789.0,
    "my_price": 20400.0,
    "my_vs_avg_pct": 33.2
  },
  "2026-03-25": {
    "vacancy": 272,
    "avg_price": 16997.0,
    "last_vacancy": 274,
    "last_avg_price": 17474.0,
    "vacancy_diff": -2,
    "avg_price_diff": -477.0,
    "my_price": 20800.0,
    "my_vs_avg_pct": 22.4
  },
  "2026-03-26": {
    "vacancy": 249,
    "avg_price": 20575.0,
    "last_vacancy": 260,
    "last_avg_price": 20314.0,
    "vacancy_diff": -11,
    "avg_price_diff": 261.0,
    "my_price": 33600.0,
    "my_vs_avg_pct": 63.3
  },
  "2026-03-27": {
    "vacancy": 205,
    "avg_price": 25315.0,
    "last_vacancy": 221,
    "last_avg_price": 24697.0,
    "vacancy_diff": -16,
    "avg_price_diff": 618.0,
    "my_price": 30300.0,
    "my_vs_avg_pct": 19.7
  },
  "2026-03-28": {
    "vacancy": 184,
    "avg_price": 28498.0,
    "last_vacancy": 191,
    "last_avg_price": 29465.0,
    "vacancy_diff": -7,
    "avg_price_diff": -967.0,
    "my_price": 39800.0,
    "my_vs_avg_pct": 39.7
  },
  "2026-03-29": {
    "vacancy": 272,
    "avg_price": 17394.0,
    "last_vacancy": 281,
    "last_avg_price": 18300.0,
    "vacancy_diff": -9,
    "avg_price_diff": -906.0,
    "my_price": 22000.0,
    "my_vs_avg_pct": 26.5
  },
  "2026-03-30": {
    "vacancy": 283,
    "avg_price": 17138.0,
    "last_vacancy": 287,
    "last_avg_price": 16894.0,
    "vacancy_diff": -4,
    "avg_price_diff": 244.0,
    "my_price": 22000.0,
    "my_vs_avg_pct": 28.4
  },
  "2026-03-31": {
    "vacancy": 263,
    "avg_price": 17088.0,
    "last_vacancy": 273,
    "last_avg_price": 17374.0,
    "vacancy_diff": -10,
    "avg_price_diff": -286.0,
    "my_price": 20800.0,
    "my_vs_avg_pct": 21.7
  },
  "2026-04-01": {
    "vacancy": 260,
    "avg_price": 20019.0,
    "last_vacancy": 272,
    "last_avg_price": 20104.0,
    "vacancy_diff": -12,
    "avg_price_diff": -85.0,
    "my_price": 22600.0,
    "my_vs_avg_pct": 12.9
  },
  "2026-04-02": {
    "vacancy": 252,
    "avg_price": 19792.0,
    "last_vacancy": 270,
    "last_avg_price": 21383.0,
    "vacancy_diff": -18,
    "avg_price_diff": -1591.0,
    "my_price": 26400.0,
    "my_vs_avg_pct": 33.4
  },
  "2026-04-03": {
    "vacancy": 248,
    "avg_price": 21116.0,
    "last_vacancy": 258,
    "last_avg_price": 22597.0,
    "vacancy_diff": -10,
    "avg_price_diff": -1481.0,
    "my_price": 24400.0,
    "my_vs_avg_pct": 15.6
  },
  "2026-04-04": {
    "vacancy": 226,
    "avg_price": 27113.0,
    "last_vacancy": 235,
    "last_avg_price": 27034.0,
    "vacancy_diff": -9,
    "avg_price_diff": 79.0,
    "my_price": 31800.0,
    "my_vs_avg_pct": 17.3
  },
  "2026-04-05": {
    "vacancy": 283,
    "avg_price": 18514.0,
    "last_vacancy": 292,
    "last_avg_price": 18849.0,
    "vacancy_diff": -9,
    "avg_price_diff": -335.0,
    "my_price": 20200.0,
    "my_vs_avg_pct": 9.1
  },
  "2026-04-06": {
    "vacancy": 283,
    "avg_price": 16989.0,
    "last_vacancy": 297,
    "last_avg_price": 18286.0,
    "vacancy_diff": -14,
    "avg_price_diff": -1297.0,
    "my_price": 21000.0,
    "my_vs_avg_pct": 23.6
  },
  "2026-04-07": {
    "vacancy": 287,
    "avg_price": 16506.0,
    "last_vacancy": 292,
    "last_avg_price": 16805.0,
    "vacancy_diff": -5,
    "avg_price_diff": -299.0,
    "my_price": 19200.0,
    "my_vs_avg_pct": 16.3
  },
  "2026-04-08": {
    "vacancy": 278,
    "avg_price": 17089.0,
    "last_vacancy": 288,
    "last_avg_price": 17198.0,
    "vacancy_diff": -10,
    "avg_price_diff": -109.0,
    "my_price": 20400.0,
    "my_vs_avg_pct": 19.4
  },
  "2026-04-09": {
    "vacancy": 265,
    "avg_price": 16901.0,
    "last_vacancy": 280,
    "last_avg_price": 17890.0,
    "vacancy_diff": -15,
    "avg_price_diff": -989.0,
    "my_price": 20400.0,
    "my_vs_avg_pct": 20.7
  },
  "2026-04-10": {
    "vacancy": 280,
    "avg_price": 17681.0,
    "last_vacancy": 290,
    "last_avg_price": 18391.0,
    "vacancy_diff": -10,
    "avg_price_diff": -710.0,
    "my_price": 33600.0,
    "my_vs_avg_pct": 90.0
  },
  "2026-04-11": {
    "vacancy": 231,
    "avg_price": 25587.0,
    "last_vacancy": 234,
    "last_avg_price": 25770.0,
    "vacancy_diff": -3,
    "avg_price_diff": -183.0,
    "my_price": 44800.0,
    "my_vs_avg_pct": 75.1
  },
  "2026-04-12": {
    "vacancy": 285,
    "avg_price": 16004.0,
    "last_vacancy": 291,
    "last_avg_price": 15698.0,
    "vacancy_diff": -6,
    "avg_price_diff": 306.0,
    "my_price": 21000.0,
    "my_vs_avg_pct": 31.2
  },
  "2026-04-13": {
    "vacancy": 284,
    "avg_price": 15308.0,
    "last_vacancy": 294,
    "last_avg_price": 16165.0,
    "vacancy_diff": -10,
    "avg_price_diff": -857.0,
    "my_price": 16800.0,
    "my_vs_avg_pct": 9.7
  },
  "2026-04-14": {
    "vacancy": 277,
    "avg_price": 16070.0,
    "last_vacancy": 286,
    "last_avg_price": 15989.0,
    "vacancy_diff": -9,
    "avg_price_diff": 81.0,
    "my_price": 20400.0,
    "my_vs_avg_pct": 26.9
  },
  "2026-04-15": {
    "vacancy": 267,
    "avg_price": 16267.0,
    "last_vacancy": 283,
    "last_avg_price": 16200.0,
    "vacancy_diff": -16,
    "avg_price_diff": 67.0,
    "my_price": 20400.0,
    "my_vs_avg_pct": 25.4
  },
  "2026-04-16": {
    "vacancy": 265,
    "avg_price": 18650.0,
    "last_vacancy": 288,
    "last_avg_price": 17494.0,
    "vacancy_diff": -23,
    "avg_price_diff": 1156.0,
    "my_price": 20400.0,
    "my_vs_avg_pct": 9.4
  },
  "2026-04-17": {
    "vacancy": 278,
    "avg_price": 17242.0,
    "last_vacancy": 284,
    "last_avg_price": 17389.0,
    "vacancy_diff": -6,
    "avg_price_diff": -147.0,
    "my_price": 21000.0,
    "my_vs_avg_pct": 21.8
  },
  "2026-04-18": {
    "vacancy": 206,
    "avg_price": 29659.0,
    "last_vacancy": 217,
    "last_avg_price": 28336.0,
    "vacancy_diff": -11,
    "avg_price_diff": 1323.0,
    "my_price": 32000.0,
    "my_vs_avg_pct": 7.9
  },
  "2026-04-19": {
    "vacancy": 291,
    "avg_price": 14406.0,
    "last_vacancy": 297,
    "last_avg_price": 14721.0,
    "vacancy_diff": -6,
    "avg_price_diff": -315.0,
    "my_price": 19200.0,
    "my_vs_avg_pct": 33.3
  },
  "2026-04-20": {
    "vacancy": 286,
    "avg_price": 15592.0,
    "last_vacancy": 297,
    "last_avg_price": 15032.0,
    "vacancy_diff": -11,
    "avg_price_diff": 560.0,
    "my_price": 18000.0,
    "my_vs_avg_pct": 15.4
  },
  "2026-04-21": {
    "vacancy": 288,
    "avg_price": 16143.0,
    "last_vacancy": 302,
    "last_avg_price": 16262.0,
    "vacancy_diff": -14,
    "avg_price_diff": -119.0,
    "my_price": 18000.0,
    "my_vs_avg_pct": 11.5
  },
  "2026-04-22": {
    "vacancy": 272,
    "avg_price": 17179.0,
    "last_vacancy": 291,
    "last_avg_price": 16863.0,
    "vacancy_diff": -19,
    "avg_price_diff": 316.0,
    "my_price": 27800.0,
    "my_vs_avg_pct": 61.8
  },
  "2026-04-23": {
    "vacancy": 284,
    "avg_price": 15706.0,
    "last_vacancy": 294,
    "last_avg_price": 16004.0,
    "vacancy_diff": -10,
    "avg_price_diff": -298.0,
    "my_price": 19200.0,
    "my_vs_avg_pct": 22.2
  },
  "2026-04-24": {
    "vacancy": 285,
    "avg_price": 16914.0,
    "last_vacancy": 297,
    "last_avg_price": 15751.0,
    "vacancy_diff": -12,
    "avg_price_diff": 1163.0,
    "my_price": 24600.0,
    "my_vs_avg_pct": 45.4
  },
  "2026-04-25": {
    "vacancy": 265,
    "avg_price": 21100.0,
    "last_vacancy": 271,
    "last_avg_price": 22755.0,
    "vacancy_diff": -6,
    "avg_price_diff": -1655.0,
    "my_price": 27300.0,
    "my_vs_avg_pct": 29.4
  },
  "2026-04-26": {
    "vacancy": 292,
    "avg_price": 13290.0,
    "last_vacancy": 300,
    "last_avg_price": 12892.0,
    "vacancy_diff": -8,
    "avg_price_diff": 398.0,
    "my_price": 15000.0,
    "my_vs_avg_pct": 12.9
  },
  "2026-04-27": {
    "vacancy": 299,
    "avg_price": 11621.0,
    "last_vacancy": 306,
    "last_avg_price": 13044.0,
    "vacancy_diff": -7,
    "avg_price_diff": -1423.0,
    "my_price": 14400.0,
    "my_vs_avg_pct": 23.9
  },
  "2026-04-28": {
    "vacancy": 300,
    "avg_price": 12269.0,
    "last_vacancy": 306,
    "last_avg_price": 11412.0,
    "vacancy_diff": -6,
    "avg_price_diff": 857.0,
    "my_price": 15000.0,
    "my_vs_avg_pct": 22.3
  },
  "2026-04-29": {
    "vacancy": 301,
    "avg_price": 13083.0,
    "last_vacancy": 313,
    "last_avg_price": 12754.0,
    "vacancy_diff": -12,
    "avg_price_diff": 329.0,
    "my_price": 15000.0,
    "my_vs_avg_pct": 14.7
  },
  "2026-04-30": {
    "vacancy": 302,
    "avg_price": 12661.0,
    "last_vacancy": 312,
    "last_avg_price": 13056.0,
    "vacancy_diff": -10,
    "avg_price_diff": -395.0,
    "my_price": 13200.0,
    "my_vs_avg_pct": 4.3
  },
  "2026-05-01": {
    "vacancy": 290,
    "avg_price": 15304.0,
    "last_vacancy": 297,
    "last_avg_price": 15429.0,
    "vacancy_diff": -7,
    "avg_price_diff": -125.0,
    "my_price": 19800.0,
    "my_vs_avg_pct": 29.4
  },
  "2026-05-02": {
    "vacancy": 239,
    "avg_price": 23365.0,
    "last_vacancy": 250,
    "last_avg_price": 23353.0,
    "vacancy_diff": -11,
    "avg_price_diff": 12.0,
    "my_price": 24400.0,
    "my_vs_avg_pct": 4.4
  },
  "2026-05-03": {
    "vacancy": 182,
    "avg_price": 24900.0,
    "last_vacancy": 201,
    "last_avg_price": 26239.0,
    "vacancy_diff": -19,
    "avg_price_diff": -1339.0,
    "my_price": 35000.0,
    "my_vs_avg_pct": 40.6
  },
  "2026-05-04": {
    "vacancy": 202,
    "avg_price": 24518.0,
    "last_vacancy": 220,
    "last_avg_price": 25156.0,
    "vacancy_diff": -18,
    "avg_price_diff": -638.0,
    "my_price": 21400.0,
    "my_vs_avg_pct": -12.7
  },
  "2026-05-05": {
    "vacancy": 274,
    "avg_price": 16360.0,
    "last_vacancy": 284,
    "last_avg_price": 17104.0,
    "vacancy_diff": -10,
    "avg_price_diff": -744.0,
    "my_price": 21400.0,
    "my_vs_avg_pct": 30.8
  },
  "2026-05-06": {
    "vacancy": 302,
    "avg_price": 11036.0,
    "last_vacancy": 308,
    "last_avg_price": 11902.0,
    "vacancy_diff": -6,
    "avg_price_diff": -866.0,
    "my_price": 15600.0,
    "my_vs_avg_pct": 41.4
  },
  "2026-05-07": {
    "vacancy": 303,
    "avg_price": 10665.0,
    "last_vacancy": 310,
    "last_avg_price": 12009.0,
    "vacancy_diff": -7,
    "avg_price_diff": -1344.0,
    "my_price": 15600.0,
    "my_vs_avg_pct": 46.3
  },
  "2026-05-08": {
    "vacancy": 292,
    "avg_price": 12665.0,
    "last_vacancy": 303,
    "last_avg_price": 12813.0,
    "vacancy_diff": -11,
    "avg_price_diff": -148.0,
    "my_price": 18000.0,
    "my_vs_avg_pct": 42.1
  },
  "2026-05-09": {
    "vacancy": 279,
    "avg_price": 17895.0,
    "last_vacancy": 283,
    "last_avg_price": 18161.0,
    "vacancy_diff": -4,
    "avg_price_diff": -266.0,
    "my_price": 22800.0,
    "my_vs_avg_pct": 27.4
  },
  "2026-05-10": {
    "vacancy": 299,
    "avg_price": 12121.0,
    "last_vacancy": 306,
    "last_avg_price": 13458.0,
    "vacancy_diff": -7,
    "avg_price_diff": -1337.0,
    "my_price": 15000.0,
    "my_vs_avg_pct": 23.8
  },
  "2026-05-11": {
    "vacancy": 295,
    "avg_price": 12759.0,
    "last_vacancy": 301,
    "last_avg_price": 13374.0,
    "vacancy_diff": -6,
    "avg_price_diff": -615.0,
    "my_price": 17800.0,
    "my_vs_avg_pct": 39.5
  },
  "2026-05-12": {
    "vacancy": 282,
    "avg_price": 14393.0,
    "last_vacancy": 290,
    "last_avg_price": 13597.0,
    "vacancy_diff": -8,
    "avg_price_diff": 796.0,
    "my_price": 24800.0,
    "my_vs_avg_pct": 72.3
  },
  "2026-05-13": {
    "vacancy": 290,
    "avg_price": 14814.0,
    "last_vacancy": 295,
    "last_avg_price": 14620.0,
    "vacancy_diff": -5,
    "avg_price_diff": 194.0,
    "my_price": 16800.0,
    "my_vs_avg_pct": 13.4
  },
  "2026-05-14": {
    "vacancy": 298,
    "avg_price": 15663.0,
    "last_vacancy": 301,
    "last_avg_price": 15465.0,
    "vacancy_diff": -3,
    "avg_price_diff": 198.0,
    "my_price": 18600.0,
    "my_vs_avg_pct": 18.8
  },
  "2026-05-15": {
    "vacancy": 283,
    "avg_price": 18019.0,
    "last_vacancy": 292,
    "last_avg_price": 18568.0,
    "vacancy_diff": -9,
    "avg_price_diff": -549.0,
    "my_price": 19200.0,
    "my_vs_avg_pct": 6.6
  },
  "2026-05-16": {
    "vacancy": 234,
    "avg_price": 26381.0,
    "last_vacancy": 245,
    "last_avg_price": 25413.0,
    "vacancy_diff": -11,
    "avg_price_diff": 968.0,
    "my_price": 32000.0,
    "my_vs_avg_pct": 21.3
  },
  "2026-05-17": {
    "vacancy": 298,
    "avg_price": 15400.0,
    "last_vacancy": 305,
    "last_avg_price": 14876.0,
    "vacancy_diff": -7,
    "avg_price_diff": 524.0,
    "my_price": 19800.0,
    "my_vs_avg_pct": 28.6
  },
  "2026-05-18": {
    "vacancy": 286,
    "avg_price": 15720.0,
    "last_vacancy": 298,
    "last_avg_price": 14855.0,
    "vacancy_diff": -12,
    "avg_price_diff": 865.0,
    "my_price": 21000.0,
    "my_vs_avg_pct": 33.6
  },
  "2026-05-19": {
    "vacancy": 280,
    "avg_price": 17556.0,
    "last_vacancy": 294,
    "last_avg_price": 16776.0,
    "vacancy_diff": -14,
    "avg_price_diff": 780.0,
    "my_price": 22400.0,
    "my_vs_avg_pct": 27.6
  },
  "2026-05-20": {
    "vacancy": 280,
    "avg_price": 18206.0,
    "last_vacancy": 294,
    "last_avg_price": 18722.0,
    "vacancy_diff": -14,
    "avg_price_diff": -516.0,
    "my_price": 20400.0,
    "my_vs_avg_pct": 12.1
  },
  "2026-05-21": {
    "vacancy": 235,
    "avg_price": 20942.0,
    "last_vacancy": 270,
    "last_avg_price": 20139.0,
    "vacancy_diff": -35,
    "avg_price_diff": 803.0,
    "my_price": 33800.0,
    "my_vs_avg_pct": 61.4
  },
  "2026-05-22": {
    "vacancy": 270,
    "avg_price": 19552.0,
    "last_vacancy": 286,
    "last_avg_price": 19803.0,
    "vacancy_diff": -16,
    "avg_price_diff": -251.0,
    "my_price": 20400.0,
    "my_vs_avg_pct": 4.3
  },
  "2026-05-23": {
    "vacancy": 122,
    "avg_price": 36295.0,
    "last_vacancy": 137,
    "last_avg_price": 38597.0,
    "vacancy_diff": -15,
    "avg_price_diff": -2302.0,
    "my_price": 39800.0,
    "my_vs_avg_pct": 9.7
  },
  "2026-05-24": {
    "vacancy": 287,
    "avg_price": 19020.0,
    "last_vacancy": 300,
    "last_avg_price": 19947.0,
    "vacancy_diff": -13,
    "avg_price_diff": -927.0,
    "my_price": 21000.0,
    "my_vs_avg_pct": 10.4
  },
  "2026-05-25": {
    "vacancy": 294,
    "avg_price": 14787.0,
    "last_vacancy": 304,
    "last_avg_price": 14706.0,
    "vacancy_diff": -10,
    "avg_price_diff": 81.0,
    "my_price": 22800.0,
    "my_vs_avg_pct": 54.2
  },
  "2026-05-26": {
    "vacancy": 291,
    "avg_price": 15288.0,
    "last_vacancy": 304,
    "last_avg_price": 14668.0,
    "vacancy_diff": -13,
    "avg_price_diff": 620.0,
    "my_price": 18000.0,
    "my_vs_avg_pct": 17.7
  },
  "2026-05-27": {
    "vacancy": 289,
    "avg_price": 16198.0,
    "last_vacancy": 304,
    "last_avg_price": 16275.0,
    "vacancy_diff": -15,
    "avg_price_diff": -77.0,
    "my_price": 22800.0,
    "my_vs_avg_pct": 40.8
  },
  "2026-05-28": {
    "vacancy": 280,
    "avg_price": 16173.0,
    "last_vacancy": 295,
    "last_avg_price": 16512.0,
    "vacancy_diff": -15,
    "avg_price_diff": -339.0,
    "my_price": 21000.0,
    "my_vs_avg_pct": 29.8
  },
  "2026-05-29": {
    "vacancy": 275,
    "avg_price": 16542.0,
    "last_vacancy": 286,
    "last_avg_price": 17588.0,
    "vacancy_diff": -11,
    "avg_price_diff": -1046.0,
    "my_price": 19200.0,
    "my_vs_avg_pct": 16.1
  },
  "2026-05-30": {
    "vacancy": 251,
    "avg_price": 22036.0,
    "last_vacancy": 268,
    "last_avg_price": 22981.0,
    "vacancy_diff": -17,
    "avg_price_diff": -945.0,
    "my_price": 28800.0,
    "my_vs_avg_pct": 30.7
  },
  "2026-05-31": {
    "vacancy": 295,
    "avg_price": 14659.0,
    "last_vacancy": 304,
    "last_avg_price": 14503.0,
    "vacancy_diff": -9,
    "avg_price_diff": 156.0,
    "my_price": 15600.0,
    "my_vs_avg_pct": 6.4
  },
  "2026-06-01": {
    "vacancy": 299,
    "avg_price": 13169.0,
    "last_vacancy": 306,
    "last_avg_price": 13763.0,
    "vacancy_diff": -7,
    "avg_price_diff": -594.0,
    "my_price": 14400.0,
    "my_vs_avg_pct": 9.3
  },
  "2026-06-02": {
    "vacancy": 293,
    "avg_price": 13313.0,
    "last_vacancy": 303,
    "last_avg_price": 13796.0,
    "vacancy_diff": -10,
    "avg_price_diff": -483.0,
    "my_price": 14400.0,
    "my_vs_avg_pct": 8.2
  },
  "2026-06-03": {
    "vacancy": 297,
    "avg_price": 13293.0,
    "last_vacancy": 303,
    "last_avg_price": 12943.0,
    "vacancy_diff": -6,
    "avg_price_diff": 350.0,
    "my_price": 14400.0,
    "my_vs_avg_pct": 8.3
  },
  "2026-06-04": {
    "vacancy": 298,
    "avg_price": 13584.0,
    "last_vacancy": 302,
    "last_avg_price": 13692.0,
    "vacancy_diff": -4,
    "avg_price_diff": -108.0,
    "my_price": 15600.0,
    "my_vs_avg_pct": 14.8
  },
  "2026-06-05": {
    "vacancy": 284,
    "avg_price": 14010.0,
    "last_vacancy": 296,
    "last_avg_price": 14165.0,
    "vacancy_diff": -12,
    "avg_price_diff": -155.0,
    "my_price": 16800.0,
    "my_vs_avg_pct": 19.9
  },
  "2026-06-06": {
    "vacancy": 258,
    "avg_price": 21976.0,
    "last_vacancy": 267,
    "last_avg_price": 21338.0,
    "vacancy_diff": -9,
    "avg_price_diff": 638.0,
    "my_price": 29000.0,
    "my_vs_avg_pct": 32.0
  },
  "2026-06-07": {
    "vacancy": 294,
    "avg_price": 12940.0,
    "last_vacancy": 299,
    "last_avg_price": 13111.0,
    "vacancy_diff": -5,
    "avg_price_diff": -171.0,
    "my_price": 15000.0,
    "my_vs_avg_pct": 15.9
  },
  "2026-06-08": {
    "vacancy": 303,
    "avg_price": 13979.0,
    "last_vacancy": 309,
    "last_avg_price": 13388.0,
    "vacancy_diff": -6,
    "avg_price_diff": 591.0,
    "my_price": 15000.0,
    "my_vs_avg_pct": 7.3
  },
  "2026-06-09": {
    "vacancy": 299,
    "avg_price": 13773.0,
    "last_vacancy": 308,
    "last_avg_price": 13933.0,
    "vacancy_diff": -9,
    "avg_price_diff": -160.0,
    "my_price": 16800.0,
    "my_vs_avg_pct": 22.0
  },
  "2026-06-10": {
    "vacancy": 308,
    "avg_price": 13864.0,
    "last_vacancy": 311,
    "last_avg_price": 13988.0,
    "vacancy_diff": -3,
    "avg_price_diff": -124.0,
    "my_price": 16800.0,
    "my_vs_avg_pct": 21.2
  },
  "2026-06-11": {
    "vacancy": 303,
    "avg_price": 15278.0,
    "last_vacancy": 311,
    "last_avg_price": 14593.0,
    "vacancy_diff": -8,
    "avg_price_diff": 685.0,
    "my_price": 16800.0,
    "my_vs_avg_pct": 10.0
  },
  "2026-06-12": {
    "vacancy": 294,
    "avg_price": 15862.0,
    "last_vacancy": 303,
    "last_avg_price": 15781.0,
    "vacancy_diff": -9,
    "avg_price_diff": 81.0,
    "my_price": 19000.0,
    "my_vs_avg_pct": 19.8
  },
  "2026-06-13": {
    "vacancy": 265,
    "avg_price": 21975.0,
    "last_vacancy": 275,
    "last_avg_price": 21850.0,
    "vacancy_diff": -10,
    "avg_price_diff": 125.0,
    "my_price": 25000.0,
    "my_vs_avg_pct": 13.8
  },
  "2026-06-14": {
    "vacancy": 303,
    "avg_price": 14380.0,
    "last_vacancy": 310,
    "last_avg_price": 14393.0,
    "vacancy_diff": -7,
    "avg_price_diff": -13.0,
    "my_price": 15600.0,
    "my_vs_avg_pct": 8.5
  },
  "2026-06-15": {
    "vacancy": 315,
    "avg_price": 14910.0,
    "last_vacancy": 320,
    "last_avg_price": 14809.0,
    "vacancy_diff": -5,
    "avg_price_diff": 101.0,
    "my_price": 16600.0,
    "my_vs_avg_pct": 11.3
  },
  "2026-06-16": {
    "vacancy": 324,
    "avg_price": 14765.0,
    "last_vacancy": 324,
    "last_avg_price": 14705.0,
    "vacancy_diff": 0,
    "avg_price_diff": 60.0,
    "my_price": 15600.0,
    "my_vs_avg_pct": 5.7
  },
  "2026-06-17": {
    "vacancy": 319,
    "avg_price": 13792.0,
    "last_vacancy": 320,
    "last_avg_price": 13822.0,
    "vacancy_diff": -1,
    "avg_price_diff": -30.0,
    "my_price": 15600.0,
    "my_vs_avg_pct": 13.1
  },
  "2026-06-18": {
    "vacancy": 320,
    "avg_price": 14542.0,
    "last_vacancy": 320,
    "last_avg_price": 14604.0,
    "vacancy_diff": 0,
    "avg_price_diff": -62.0,
    "my_price": 16800.0,
    "my_vs_avg_pct": 15.5
  },
  "2026-06-19": {
    "vacancy": 313,
    "avg_price": 16965.0,
    "last_vacancy": 314,
    "last_avg_price": 17351.0,
    "vacancy_diff": -1,
    "avg_price_diff": -386.0,
    "my_price": 18000.0,
    "my_vs_avg_pct": 6.1
  },
  "2026-06-20": {
    "vacancy": 297,
    "avg_price": 23422.0,
    "last_vacancy": 297,
    "last_avg_price": 23351.0,
    "vacancy_diff": 0,
    "avg_price_diff": 71.0,
    "my_price": 25200.0,
    "my_vs_avg_pct": 7.6
  },
  "2026-06-21": {
    "vacancy": 328,
    "avg_price": 14952.0,
    "last_vacancy": 327,
    "last_avg_price": 14993.0,
    "vacancy_diff": 1,
    "avg_price_diff": -41.0,
    "my_price": 15000.0,
    "my_vs_avg_pct": 0.3
  },
  "2026-06-22": {
    "vacancy": 323,
    "avg_price": 14447.0,
    "last_vacancy": 323,
    "last_avg_price": 14458.0,
    "vacancy_diff": 0,
    "avg_price_diff": -11.0,
    "my_price": 15000.0,
    "my_vs_avg_pct": 3.8
  },
  "2026-06-23": {
    "vacancy": 323,
    "avg_price": 14872.0,
    "last_vacancy": 323,
    "last_avg_price": 14742.0,
    "vacancy_diff": 0,
    "avg_price_diff": 130.0,
    "my_price": 15600.0,
    "my_vs_avg_pct": 4.9
  },
  "2026-06-24": {
    "vacancy": 321,
    "avg_price": 14884.0,
    "last_vacancy": 321,
    "last_avg_price": 14811.0,
    "vacancy_diff": 0,
    "avg_price_diff": 73.0,
    "my_price": 15600.0,
    "my_vs_avg_pct": 4.8
  },
  "2026-06-25": {
    "vacancy": 323,
    "avg_price": 15150.0,
    "last_vacancy": 322,
    "last_avg_price": 15081.0,
    "vacancy_diff": 1,
    "avg_price_diff": 69.0,
    "my_price": 15600.0,
    "my_vs_avg_pct": 3.0
  },
  "2026-06-26": {
    "vacancy": 314,
    "avg_price": 16494.0,
    "last_vacancy": 314,
    "last_avg_price": 16373.0,
    "vacancy_diff": 0,
    "avg_price_diff": 121.0,
    "my_price": 18000.0,
    "my_vs_avg_pct": 9.1
  },
  "2026-06-27": {
    "vacancy": 288,
    "avg_price": 23939.0,
    "last_vacancy": 288,
    "last_avg_price": 24301.0,
    "vacancy_diff": 0,
    "avg_price_diff": -362.0,
    "my_price": 25000.0,
    "my_vs_avg_pct": 4.4
  },
  "2026-06-28": {
    "vacancy": 319,
    "avg_price": 15241.0,
    "last_vacancy": 318,
    "last_avg_price": 14166.0,
    "vacancy_diff": 1,
    "avg_price_diff": 1075.0,
    "my_price": 15000.0,
    "my_vs_avg_pct": -1.6
  },
  "2026-06-29": {
    "vacancy": 321,
    "avg_price": 14353.0,
    "last_vacancy": 320,
    "last_avg_price": 14304.0,
    "vacancy_diff": 1,
    "avg_price_diff": 49.0,
    "my_price": 14400.0,
    "my_vs_avg_pct": 0.3
  },
  "2026-06-30": {
    "vacancy": 318,
    "avg_price": 14569.0,
    "last_vacancy": 317,
    "last_avg_price": 14081.0,
    "vacancy_diff": 1,
    "avg_price_diff": 488.0,
    "my_price": 14400.0,
    "my_vs_avg_pct": -1.2
  },
  "2026-07-01": {
    "vacancy": 321,
    "avg_price": 15216.0,
    "last_vacancy": 321,
    "last_avg_price": 15471.0,
    "vacancy_diff": 0,
    "avg_price_diff": -255.0,
    "my_price": 18000.0,
    "my_vs_avg_pct": 18.3
  },
  "2026-07-02": {
    "vacancy": 323,
    "avg_price": 15884.0,
    "last_vacancy": 322,
    "last_avg_price": 15961.0,
    "vacancy_diff": 1,
    "avg_price_diff": -77.0,
    "my_price": 18000.0,
    "my_vs_avg_pct": 13.3
  },
  "2026-07-03": {
    "vacancy": 325,
    "avg_price": 16388.0,
    "last_vacancy": 322,
    "last_avg_price": 16324.0,
    "vacancy_diff": 3,
    "avg_price_diff": 64.0,
    "my_price": 18000.0,
    "my_vs_avg_pct": 9.8
  },
  "2026-07-04": {
    "vacancy": 306,
    "avg_price": 22659.0,
    "last_vacancy": 307,
    "last_avg_price": 22930.0,
    "vacancy_diff": -1,
    "avg_price_diff": -271.0,
    "my_price": 24400.0,
    "my_vs_avg_pct": 7.7
  },
  "2026-07-05": {
    "vacancy": 330,
    "avg_price": 15253.0,
    "last_vacancy": 328,
    "last_avg_price": 15062.0,
    "vacancy_diff": 2,
    "avg_price_diff": 191.0,
    "my_price": 15000.0,
    "my_vs_avg_pct": -1.7
  },
  "2026-07-06": {
    "vacancy": 329,
    "avg_price": 15151.0,
    "last_vacancy": 328,
    "last_avg_price": 15064.0,
    "vacancy_diff": 1,
    "avg_price_diff": 87.0,
    "my_price": 15000.0,
    "my_vs_avg_pct": -1.0
  },
  "2026-07-07": {
    "vacancy": 323,
    "avg_price": 15254.0,
    "last_vacancy": 322,
    "last_avg_price": 15194.0,
    "vacancy_diff": 1,
    "avg_price_diff": 60.0,
    "my_price": 16800.0,
    "my_vs_avg_pct": 10.1
  },
  "2026-07-08": {
    "vacancy": 326,
    "avg_price": 14764.0,
    "last_vacancy": 324,
    "last_avg_price": 14790.0,
    "vacancy_diff": 2,
    "avg_price_diff": -26.0,
    "my_price": 15600.0,
    "my_vs_avg_pct": 5.7
  },
  "2026-07-09": {
    "vacancy": 329,
    "avg_price": 15204.0,
    "last_vacancy": 326,
    "last_avg_price": 15223.0,
    "vacancy_diff": 3,
    "avg_price_diff": -19.0,
    "my_price": 15600.0,
    "my_vs_avg_pct": 2.6
  },
  "2026-07-10": {
    "vacancy": 327,
    "avg_price": 15902.0,
    "last_vacancy": 326,
    "last_avg_price": 15864.0,
    "vacancy_diff": 1,
    "avg_price_diff": 38.0,
    "my_price": 18000.0,
    "my_vs_avg_pct": 13.2
  },
  "2026-07-11": {
    "vacancy": 303,
    "avg_price": 24246.0,
    "last_vacancy": 302,
    "last_avg_price": 24172.0,
    "vacancy_diff": 1,
    "avg_price_diff": 74.0,
    "my_price": 24400.0,
    "my_vs_avg_pct": 0.6
  },
  "2026-07-12": {
    "vacancy": 328,
    "avg_price": 15833.0,
    "last_vacancy": 325,
    "last_avg_price": 15788.0,
    "vacancy_diff": 3,
    "avg_price_diff": 45.0,
    "my_price": 15600.0,
    "my_vs_avg_pct": -1.5
  },
  "2026-07-13": {
    "vacancy": 326,
    "avg_price": 15166.0,
    "last_vacancy": 324,
    "last_avg_price": 15074.0,
    "vacancy_diff": 2,
    "avg_price_diff": 92.0,
    "my_price": 15000.0,
    "my_vs_avg_pct": -1.1
  },
  "2026-07-14": {
    "vacancy": 329,
    "avg_price": 15502.0,
    "last_vacancy": 328,
    "last_avg_price": 15566.0,
    "vacancy_diff": 1,
    "avg_price_diff": -64.0,
    "my_price": 15000.0,
    "my_vs_avg_pct": -3.2
  },
  "2026-07-15": {
    "vacancy": 330,
    "avg_price": 15469.0,
    "last_vacancy": 329,
    "last_avg_price": 15442.0,
    "vacancy_diff": 1,
    "avg_price_diff": 27.0,
    "my_price": 15600.0,
    "my_vs_avg_pct": 0.8
  },
  "2026-07-16": {
    "vacancy": 329,
    "avg_price": 15695.0,
    "last_vacancy": 328,
    "last_avg_price": 15707.0,
    "vacancy_diff": 1,
    "avg_price_diff": -12.0,
    "my_price": 16800.0,
    "my_vs_avg_pct": 7.0
  },
  "2026-07-17": {
    "vacancy": 328,
    "avg_price": 17000.0,
    "last_vacancy": 327,
    "last_avg_price": 17112.0,
    "vacancy_diff": 1,
    "avg_price_diff": -112.0,
    "my_price": 18000.0,
    "my_vs_avg_pct": 5.9
  },
  "2026-07-18": {
    "vacancy": 294,
    "avg_price": 26196.0,
    "last_vacancy": 294,
    "last_avg_price": 26520.0,
    "vacancy_diff": 0,
    "avg_price_diff": -324.0,
    "my_price": 24400.0,
    "my_vs_avg_pct": -6.9
  },
  "2026-07-19": {
    "vacancy": 309,
    "avg_price": 23613.0,
    "last_vacancy": 308,
    "last_avg_price": 23633.0,
    "vacancy_diff": 1,
    "avg_price_diff": -20.0,
    "my_price": 25200.0,
    "my_vs_avg_pct": 6.7
  },
  "2026-07-20": {
    "vacancy": 330,
    "avg_price": 15700.0,
    "last_vacancy": 329,
    "last_avg_price": 15734.0,
    "vacancy_diff": 1,
    "avg_price_diff": -34.0,
    "my_price": 15000.0,
    "my_vs_avg_pct": -4.5
  },
  "2026-07-21": {
    "vacancy": 327,
    "avg_price": 15672.0,
    "last_vacancy": 327,
    "last_avg_price": 15776.0,
    "vacancy_diff": 0,
    "avg_price_diff": -104.0,
    "my_price": 18000.0,
    "my_vs_avg_pct": 14.9
  },
  "2026-07-22": {
    "vacancy": 323,
    "avg_price": 17552.0,
    "last_vacancy": 321,
    "last_avg_price": 17499.0,
    "vacancy_diff": 2,
    "avg_price_diff": 53.0,
    "my_price": 23800.0,
    "my_vs_avg_pct": 35.6
  },
  "2026-07-23": {
    "vacancy": 327,
    "avg_price": 17431.0,
    "last_vacancy": 326,
    "last_avg_price": 17581.0,
    "vacancy_diff": 1,
    "avg_price_diff": -150.0,
    "my_price": 20400.0,
    "my_vs_avg_pct": 17.0
  },
  "2026-07-24": {
    "vacancy": 321,
    "avg_price": 17750.0,
    "last_vacancy": 320,
    "last_avg_price": 17994.0,
    "vacancy_diff": 1,
    "avg_price_diff": -244.0,
    "my_price": 19200.0,
    "my_vs_avg_pct": 8.2
  },
  "2026-07-25": {
    "vacancy": 308,
    "avg_price": 24426.0,
    "last_vacancy": 306,
    "last_avg_price": 24946.0,
    "vacancy_diff": 2,
    "avg_price_diff": -520.0,
    "my_price": 25000.0,
    "my_vs_avg_pct": 2.3
  },
  "2026-07-26": {
    "vacancy": 327,
    "avg_price": 16219.0,
    "last_vacancy": 327,
    "last_avg_price": 16403.0,
    "vacancy_diff": 0,
    "avg_price_diff": -184.0,
    "my_price": 15000.0,
    "my_vs_avg_pct": -7.5
  },
  "2026-07-27": {
    "vacancy": 326,
    "avg_price": 16276.0,
    "last_vacancy": 326,
    "last_avg_price": 16313.0,
    "vacancy_diff": 0,
    "avg_price_diff": -37.0,
    "my_price": 15000.0,
    "my_vs_avg_pct": -7.8
  },
  "2026-07-28": {
    "vacancy": 323,
    "avg_price": 16668.0,
    "last_vacancy": 323,
    "last_avg_price": 17016.0,
    "vacancy_diff": 0,
    "avg_price_diff": -348.0,
    "my_price": 15000.0,
    "my_vs_avg_pct": -10.0
  },
  "2026-07-29": {
    "vacancy": 326,
    "avg_price": 16759.0,
    "last_vacancy": 324,
    "last_avg_price": 17050.0,
    "vacancy_diff": 2,
    "avg_price_diff": -291.0,
    "my_price": 15600.0,
    "my_vs_avg_pct": -6.9
  },
  "2026-07-30": {
    "vacancy": 327,
    "avg_price": 16383.0,
    "last_vacancy": 325,
    "last_avg_price": 16621.0,
    "vacancy_diff": 2,
    "avg_price_diff": -238.0,
    "my_price": 15600.0,
    "my_vs_avg_pct": -4.8
  },
  "2026-07-31": {
    "vacancy": 323,
    "avg_price": 17255.0,
    "last_vacancy": 321,
    "last_avg_price": 17593.0,
    "vacancy_diff": 2,
    "avg_price_diff": -338.0,
    "my_price": 19200.0,
    "my_vs_avg_pct": 11.3
  },
  "2026-08-01": {
    "vacancy": 304,
    "avg_price": 25902.0,
    "last_vacancy": 301,
    "last_avg_price": 25653.0,
    "vacancy_diff": 3,
    "avg_price_diff": 249.0,
    "my_price": 25600.0,
    "my_vs_avg_pct": -1.2
  },
  "2026-08-02": {
    "vacancy": 322,
    "avg_price": 17396.0,
    "last_vacancy": 321,
    "last_avg_price": 17407.0,
    "vacancy_diff": 1,
    "avg_price_diff": -11.0,
    "my_price": 18000.0,
    "my_vs_avg_pct": 3.5
  },
  "2026-08-03": {
    "vacancy": 331,
    "avg_price": 16688.0,
    "last_vacancy": 330,
    "last_avg_price": 16687.0,
    "vacancy_diff": 1,
    "avg_price_diff": 1.0,
    "my_price": 16800.0,
    "my_vs_avg_pct": 0.7
  },
  "2026-08-04": {
    "vacancy": 330,
    "avg_price": 16772.0,
    "last_vacancy": 330,
    "last_avg_price": 16832.0,
    "vacancy_diff": 0,
    "avg_price_diff": -60.0,
    "my_price": 16800.0,
    "my_vs_avg_pct": 0.2
  },
  "2026-08-05": {
    "vacancy": 332,
    "avg_price": 16593.0,
    "last_vacancy": 331,
    "last_avg_price": 16559.0,
    "vacancy_diff": 1,
    "avg_price_diff": 34.0,
    "my_price": 16800.0,
    "my_vs_avg_pct": 1.2
  },
  "2026-08-06": {
    "vacancy": 334,
    "avg_price": 16511.0,
    "last_vacancy": 333,
    "last_avg_price": 16546.0,
    "vacancy_diff": 1,
    "avg_price_diff": -35.0,
    "my_price": 16800.0,
    "my_vs_avg_pct": 1.8
  },
  "2026-08-07": {
    "vacancy": 331,
    "avg_price": 17544.0,
    "last_vacancy": 330,
    "last_avg_price": 17306.0,
    "vacancy_diff": 1,
    "avg_price_diff": 238.0,
    "my_price": 19200.0,
    "my_vs_avg_pct": 9.4
  },
  "2026-08-08": {
    "vacancy": 313,
    "avg_price": 24863.0,
    "last_vacancy": 312,
    "last_avg_price": 24741.0,
    "vacancy_diff": 1,
    "avg_price_diff": 122.0,
    "my_price": 25600.0,
    "my_vs_avg_pct": 3.0
  },
  "2026-08-09": {
    "vacancy": 326,
    "avg_price": 19241.0,
    "last_vacancy": 325,
    "last_avg_price": 18949.0,
    "vacancy_diff": 1,
    "avg_price_diff": 292.0,
    "my_price": 18000.0,
    "my_vs_avg_pct": -6.4
  },
  "2026-08-10": {
    "vacancy": 325,
    "avg_price": 18754.0,
    "last_vacancy": 324,
    "last_avg_price": 18626.0,
    "vacancy_diff": 1,
    "avg_price_diff": 128.0,
    "my_price": 18000.0,
    "my_vs_avg_pct": -4.0
  },
  "2026-08-11": {
    "vacancy": 324,
    "avg_price": 18920.0,
    "last_vacancy": 324,
    "last_avg_price": 18770.0,
    "vacancy_diff": 0,
    "avg_price_diff": 150.0,
    "my_price": 18000.0,
    "my_vs_avg_pct": -4.9
  },
  "2026-08-12": {
    "vacancy": 325,
    "avg_price": 18664.0,
    "last_vacancy": 324,
    "last_avg_price": 18535.0,
    "vacancy_diff": 1,
    "avg_price_diff": 129.0,
    "my_price": 24600.0,
    "my_vs_avg_pct": 31.8
  },
  "2026-08-13": {
    "vacancy": 322,
    "avg_price": 19422.0,
    "last_vacancy": 322,
    "last_avg_price": 19340.0,
    "vacancy_diff": 0,
    "avg_price_diff": 82.0,
    "my_price": 25600.0,
    "my_vs_avg_pct": 31.8
  },
  "2026-08-14": {
    "vacancy": 320,
    "avg_price": 19701.0,
    "last_vacancy": 318,
    "last_avg_price": 19495.0,
    "vacancy_diff": 2,
    "avg_price_diff": 206.0,
    "my_price": 25600.0,
    "my_vs_avg_pct": 29.9
  },
  "2026-08-15": {
    "vacancy": 316,
    "avg_price": 23241.0,
    "last_vacancy": 316,
    "last_avg_price": 23078.0,
    "vacancy_diff": 0,
    "avg_price_diff": 163.0,
    "my_price": 25600.0,
    "my_vs_avg_pct": 10.2
  },
  "2026-08-16": {
    "vacancy": 332,
    "avg_price": 15741.0,
    "last_vacancy": 331,
    "last_avg_price": 15662.0,
    "vacancy_diff": 1,
    "avg_price_diff": 79.0,
    "my_price": 15000.0,
    "my_vs_avg_pct": -4.7
  },
  "2026-08-17": {
    "vacancy": 330,
    "avg_price": 15443.0,
    "last_vacancy": 329,
    "last_avg_price": 15389.0,
    "vacancy_diff": 1,
    "avg_price_diff": 54.0,
    "my_price": 15000.0,
    "my_vs_avg_pct": -2.9
  },
  "2026-08-18": {
    "vacancy": 330,
    "avg_price": 15760.0,
    "last_vacancy": 330,
    "last_avg_price": 15768.0,
    "vacancy_diff": 0,
    "avg_price_diff": -8.0,
    "my_price": 15600.0,
    "my_vs_avg_pct": -1.0
  },
  "2026-08-19": {
    "vacancy": 330,
    "avg_price": 16007.0,
    "last_vacancy": 330,
    "last_avg_price": 15998.0,
    "vacancy_diff": 0,
    "avg_price_diff": 9.0,
    "my_price": 15600.0,
    "my_vs_avg_pct": -2.5
  },
  "2026-08-20": {
    "vacancy": 330,
    "avg_price": 16310.0,
    "last_vacancy": 330,
    "last_avg_price": 16164.0,
    "vacancy_diff": 0,
    "avg_price_diff": 146.0,
    "my_price": 15600.0,
    "my_vs_avg_pct": -4.4
  },
  "2026-08-21": {
    "vacancy": 334,
    "avg_price": 17166.0,
    "last_vacancy": 333,
    "last_avg_price": 16972.0,
    "vacancy_diff": 1,
    "avg_price_diff": 194.0,
    "my_price": 18000.0,
    "my_vs_avg_pct": 4.9
  },
  "2026-08-22": {
    "vacancy": 319,
    "avg_price": 23700.0,
    "last_vacancy": 318,
    "last_avg_price": 23691.0,
    "vacancy_diff": 1,
    "avg_price_diff": 9.0,
    "my_price": 25600.0,
    "my_vs_avg_pct": 8.0
  },
  "2026-08-23": {
    "vacancy": 334,
    "avg_price": 16233.0,
    "last_vacancy": 333,
    "last_avg_price": 16079.0,
    "vacancy_diff": 1,
    "avg_price_diff": 154.0,
    "my_price": 16800.0,
    "my_vs_avg_pct": 3.5
  },
  "2026-08-24": {
    "vacancy": 332,
    "avg_price": 15325.0,
    "last_vacancy": 331,
    "last_avg_price": 15239.0,
    "vacancy_diff": 1,
    "avg_price_diff": 86.0,
    "my_price": 16800.0,
    "my_vs_avg_pct": 9.6
  },
  "2026-08-25": {
    "vacancy": 334,
    "avg_price": 15739.0,
    "last_vacancy": 333,
    "last_avg_price": 15596.0,
    "vacancy_diff": 1,
    "avg_price_diff": 143.0,
    "my_price": 15600.0,
    "my_vs_avg_pct": -0.9
  },
  "2026-08-26": {
    "vacancy": 330,
    "avg_price": 15500.0,
    "last_vacancy": 329,
    "last_avg_price": 15433.0,
    "vacancy_diff": 1,
    "avg_price_diff": 67.0,
    "my_price": 15600.0,
    "my_vs_avg_pct": 0.6
  },
  "2026-08-27": {
    "vacancy": 333,
    "avg_price": 15547.0,
    "last_vacancy": 332,
    "last_avg_price": 15508.0,
    "vacancy_diff": 1,
    "avg_price_diff": 39.0,
    "my_price": 15600.0,
    "my_vs_avg_pct": 0.3
  },
  "2026-08-28": {
    "vacancy": 332,
    "avg_price": 16699.0,
    "last_vacancy": 331,
    "last_avg_price": 16592.0,
    "vacancy_diff": 1,
    "avg_price_diff": 107.0,
    "my_price": 18000.0,
    "my_vs_avg_pct": 7.8
  },
  "2026-08-29": {
    "vacancy": 326,
    "avg_price": 23112.0,
    "last_vacancy": 325,
    "last_avg_price": 23022.0,
    "vacancy_diff": 1,
    "avg_price_diff": 90.0,
    "my_price": 25600.0,
    "my_vs_avg_pct": 10.8
  },
  "2026-08-30": {
    "vacancy": 334,
    "avg_price": 15207.0,
    "last_vacancy": 333,
    "last_avg_price": 15081.0,
    "vacancy_diff": 1,
    "avg_price_diff": 126.0,
    "my_price": 15000.0,
    "my_vs_avg_pct": -1.4
  },
  "2026-08-31": {
    "vacancy": 334,
    "avg_price": 14829.0,
    "last_vacancy": 333,
    "last_avg_price": 14726.0,
    "vacancy_diff": 1,
    "avg_price_diff": 103.0,
    "my_price": 15000.0,
    "my_vs_avg_pct": 1.2
  },
  "2026-09-01": {
    "vacancy": 322,
    "avg_price": 15222.0,
    "last_vacancy": 321,
    "last_avg_price": 15431.0,
    "vacancy_diff": 1,
    "avg_price_diff": -209.0,
    "my_price": 15000.0,
    "my_vs_avg_pct": -1.5
  },
  "2026-09-02": {
    "vacancy": 324,
    "avg_price": 15234.0,
    "last_vacancy": 323,
    "last_avg_price": 15343.0,
    "vacancy_diff": 1,
    "avg_price_diff": -109.0,
    "my_price": 15600.0,
    "my_vs_avg_pct": 2.4
  },
  "2026-09-03": {
    "vacancy": 323,
    "avg_price": 15386.0,
    "last_vacancy": 322,
    "last_avg_price": 15520.0,
    "vacancy_diff": 1,
    "avg_price_diff": -134.0,
    "my_price": 15600.0,
    "my_vs_avg_pct": 1.4
  },
  "2026-09-04": {
    "vacancy": 322,
    "avg_price": 16791.0,
    "last_vacancy": 321,
    "last_avg_price": 16865.0,
    "vacancy_diff": 1,
    "avg_price_diff": -74.0,
    "my_price": 19200.0,
    "my_vs_avg_pct": 14.3
  },
  "2026-09-05": {
    "vacancy": 316,
    "avg_price": 22659.0,
    "last_vacancy": 315,
    "last_avg_price": 22693.0,
    "vacancy_diff": 1,
    "avg_price_diff": -34.0,
    "my_price": 22600.0,
    "my_vs_avg_pct": -0.3
  },
  "2026-09-06": {
    "vacancy": 325,
    "avg_price": 15166.0,
    "last_vacancy": 324,
    "last_avg_price": 15255.0,
    "vacancy_diff": 1,
    "avg_price_diff": -89.0,
    "my_price": 15000.0,
    "my_vs_avg_pct": -1.1
  },
  "2026-09-07": {
    "vacancy": 322,
    "avg_price": 14981.0,
    "last_vacancy": 321,
    "last_avg_price": 15057.0,
    "vacancy_diff": 1,
    "avg_price_diff": -76.0,
    "my_price": 15000.0,
    "my_vs_avg_pct": 0.1
  },
  "2026-09-08": {
    "vacancy": 324,
    "avg_price": 15528.0,
    "last_vacancy": 323,
    "last_avg_price": 15597.0,
    "vacancy_diff": 1,
    "avg_price_diff": -69.0,
    "my_price": 15000.0,
    "my_vs_avg_pct": -3.4
  },
  "2026-09-09": {
    "vacancy": 323,
    "avg_price": 15767.0,
    "last_vacancy": 323,
    "last_avg_price": 15779.0,
    "vacancy_diff": 0,
    "avg_price_diff": -12.0,
    "my_price": 15600.0,
    "my_vs_avg_pct": -1.1
  },
  "2026-09-10": {
    "vacancy": 323,
    "avg_price": 16001.0,
    "last_vacancy": 322,
    "last_avg_price": 15928.0,
    "vacancy_diff": 1,
    "avg_price_diff": 73.0,
    "my_price": 15600.0,
    "my_vs_avg_pct": -2.5
  },
  "2026-09-11": {
    "vacancy": 325,
    "avg_price": 17318.0,
    "last_vacancy": 324,
    "last_avg_price": 17278.0,
    "vacancy_diff": 1,
    "avg_price_diff": 40.0,
    "my_price": 18000.0,
    "my_vs_avg_pct": 3.9
  },
  "2026-09-12": {
    "vacancy": 316,
    "avg_price": 23766.0,
    "last_vacancy": 315,
    "last_avg_price": 23879.0,
    "vacancy_diff": 1,
    "avg_price_diff": -113.0,
    "my_price": 22600.0,
    "my_vs_avg_pct": -4.9
  },
  "2026-09-13": {
    "vacancy": 324,
    "avg_price": 15643.0,
    "last_vacancy": 323,
    "last_avg_price": 15750.0,
    "vacancy_diff": 1,
    "avg_price_diff": -107.0,
    "my_price": 15000.0,
    "my_vs_avg_pct": -4.1
  },
  "2026-09-14": {
    "vacancy": 324,
    "avg_price": 15392.0,
    "last_vacancy": 323,
    "last_avg_price": 15450.0,
    "vacancy_diff": 1,
    "avg_price_diff": -58.0,
    "my_price": 15000.0,
    "my_vs_avg_pct": -2.5
  },
  "2026-09-15": {
    "vacancy": 322,
    "avg_price": 15670.0,
    "last_vacancy": 321,
    "last_avg_price": 15734.0,
    "vacancy_diff": 1,
    "avg_price_diff": -64.0,
    "my_price": 15000.0,
    "my_vs_avg_pct": -4.3
  },
  "2026-09-16": {
    "vacancy": 322,
    "avg_price": 15752.0,
    "last_vacancy": 321,
    "last_avg_price": 15847.0,
    "vacancy_diff": 1,
    "avg_price_diff": -95.0,
    "my_price": 15600.0,
    "my_vs_avg_pct": -1.0
  },
  "2026-09-17": {
    "vacancy": 321,
    "avg_price": 15868.0,
    "last_vacancy": 320,
    "last_avg_price": 15948.0,
    "vacancy_diff": 1,
    "avg_price_diff": -80.0,
    "my_price": 15600.0,
    "my_vs_avg_pct": -1.7
  },
  "2026-09-18": {
    "vacancy": 321,
    "avg_price": 17964.0,
    "last_vacancy": 320,
    "last_avg_price": 17945.0,
    "vacancy_diff": 1,
    "avg_price_diff": 19.0,
    "my_price": 19200.0,
    "my_vs_avg_pct": 6.9
  },
  "2026-09-19": {
    "vacancy": 304,
    "avg_price": 27518.0,
    "last_vacancy": 302,
    "last_avg_price": 27867.0,
    "vacancy_diff": 2,
    "avg_price_diff": -349.0,
    "my_price": 28800.0,
    "my_vs_avg_pct": 4.7
  },
  "2026-09-20": {
    "vacancy": 301,
    "avg_price": 27768.0,
    "last_vacancy": 302,
    "last_avg_price": 28065.0,
    "vacancy_diff": -1,
    "avg_price_diff": -297.0,
    "my_price": 28800.0,
    "my_vs_avg_pct": 3.7
  },
  "2026-09-21": {
    "vacancy": 310,
    "avg_price": 26465.0,
    "last_vacancy": 309,
    "last_avg_price": 26985.0,
    "vacancy_diff": 1,
    "avg_price_diff": -520.0,
    "my_price": 27300.0,
    "my_vs_avg_pct": 3.2
  },
  "2026-09-22": {
    "vacancy": 314,
    "avg_price": 23704.0,
    "last_vacancy": 313,
    "last_avg_price": 23755.0,
    "vacancy_diff": 1,
    "avg_price_diff": -51.0,
    "my_price": 24400.0,
    "my_vs_avg_pct": 2.9
  },
  "2026-09-23": {
    "vacancy": 319,
    "avg_price": 16525.0,
    "last_vacancy": 318,
    "last_avg_price": 16669.0,
    "vacancy_diff": 1,
    "avg_price_diff": -144.0,
    "my_price": 15600.0,
    "my_vs_avg_pct": -5.6
  },
  "2026-09-24": {
    "vacancy": 316,
    "avg_price": 16671.0,
    "last_vacancy": 315,
    "last_avg_price": 16741.0,
    "vacancy_diff": 1,
    "avg_price_diff": -70.0,
    "my_price": 15600.0,
    "my_vs_avg_pct": -6.4
  },
  "2026-09-25": {
    "vacancy": 319,
    "avg_price": 18629.0,
    "last_vacancy": 318,
    "last_avg_price": 18679.0,
    "vacancy_diff": 1,
    "avg_price_diff": -50.0,
    "my_price": 19200.0,
    "my_vs_avg_pct": 3.1
  },
  "2026-09-26": {
    "vacancy": 309,
    "avg_price": 25640.0,
    "last_vacancy": 308,
    "last_avg_price": 25920.0,
    "vacancy_diff": 1,
    "avg_price_diff": -280.0,
    "my_price": 24400.0,
    "my_vs_avg_pct": -4.8
  },
  "2026-09-27": {
    "vacancy": 319,
    "avg_price": 17068.0,
    "last_vacancy": 318,
    "last_avg_price": 17116.0,
    "vacancy_diff": 1,
    "avg_price_diff": -48.0,
    "my_price": 15000.0,
    "my_vs_avg_pct": -12.1
  },
  "2026-09-28": {
    "vacancy": 322,
    "avg_price": 16141.0,
    "last_vacancy": 321,
    "last_avg_price": 16254.0,
    "vacancy_diff": 1,
    "avg_price_diff": -113.0,
    "my_price": 15000.0,
    "my_vs_avg_pct": -7.1
  },
  "2026-09-29": {
    "vacancy": 323,
    "avg_price": 15919.0,
    "last_vacancy": 322,
    "last_avg_price": 16067.0,
    "vacancy_diff": 1,
    "avg_price_diff": -148.0,
    "my_price": 15600.0,
    "my_vs_avg_pct": -2.0
  },
  "2026-09-30": {
    "vacancy": 322,
    "avg_price": 16140.0,
    "last_vacancy": 321,
    "last_avg_price": 16217.0,
    "vacancy_diff": 1,
    "avg_price_diff": -77.0,
    "my_price": 15600.0,
    "my_vs_avg_pct": -3.3
  },
  "2026-10-01": {
    "vacancy": 310,
    "avg_price": 19239.0,
    "last_vacancy": 309,
    "last_avg_price": 19400.0,
    "vacancy_diff": 1,
    "avg_price_diff": -161.0,
    "my_price": 15600.0,
    "my_vs_avg_pct": -18.9
  },
  "2026-10-02": {
    "vacancy": 310,
    "avg_price": 20889.0,
    "last_vacancy": 309,
    "last_avg_price": 20898.0,
    "vacancy_diff": 1,
    "avg_price_diff": -9.0,
    "my_price": 19200.0,
    "my_vs_avg_pct": -8.1
  },
  "2026-10-03": {
    "vacancy": 300,
    "avg_price": 28101.0,
    "last_vacancy": 300,
    "last_avg_price": 28143.0,
    "vacancy_diff": 0,
    "avg_price_diff": -42.0,
    "my_price": 25600.0,
    "my_vs_avg_pct": -8.9
  },
  "2026-10-04": {
    "vacancy": 309,
    "avg_price": 18700.0,
    "last_vacancy": 307,
    "last_avg_price": 18869.0,
    "vacancy_diff": 2,
    "avg_price_diff": -169.0,
    "my_price": 15600.0,
    "my_vs_avg_pct": -16.6
  },
  "2026-10-05": {
    "vacancy": 308,
    "avg_price": 18682.0,
    "last_vacancy": 306,
    "last_avg_price": 18954.0,
    "vacancy_diff": 2,
    "avg_price_diff": -272.0,
    "my_price": 15600.0,
    "my_vs_avg_pct": -16.5
  },
  "2026-10-06": {
    "vacancy": 307,
    "avg_price": 19035.0,
    "last_vacancy": 306,
    "last_avg_price": 19246.0,
    "vacancy_diff": 1,
    "avg_price_diff": -211.0,
    "my_price": 15600.0,
    "my_vs_avg_pct": -18.0
  },
  "2026-10-07": {
    "vacancy": 309,
    "avg_price": 19402.0,
    "last_vacancy": 308,
    "last_avg_price": 20543.0,
    "vacancy_diff": 1,
    "avg_price_diff": -1141.0,
    "my_price": 15600.0,
    "my_vs_avg_pct": -19.6
  },
  "2026-10-08": {
    "vacancy": 310,
    "avg_price": 19773.0,
    "last_vacancy": 308,
    "last_avg_price": 20851.0,
    "vacancy_diff": 2,
    "avg_price_diff": -1078.0,
    "my_price": 15600.0,
    "my_vs_avg_pct": -21.1
  },
  "2026-10-09": {
    "vacancy": 307,
    "avg_price": 20959.0,
    "last_vacancy": 306,
    "last_avg_price": 20950.0,
    "vacancy_diff": 1,
    "avg_price_diff": 9.0,
    "my_price": 18000.0,
    "my_vs_avg_pct": -14.1
  },
  "2026-10-10": {
    "vacancy": 295,
    "avg_price": 29492.0,
    "last_vacancy": 294,
    "last_avg_price": 29514.0,
    "vacancy_diff": 1,
    "avg_price_diff": -22.0,
    "my_price": 25600.0,
    "my_vs_avg_pct": -13.2
  },
  "2026-10-11": {
    "vacancy": 300,
    "avg_price": 27638.0,
    "last_vacancy": 299,
    "last_avg_price": 27681.0,
    "vacancy_diff": 1,
    "avg_price_diff": -43.0,
    "my_price": 25000.0,
    "my_vs_avg_pct": -9.5
  },
  "2026-10-12": {
    "vacancy": 307,
    "avg_price": 17904.0,
    "last_vacancy": 306,
    "last_avg_price": 18166.0,
    "vacancy_diff": 1,
    "avg_price_diff": -262.0,
    "my_price": 15000.0,
    "my_vs_avg_pct": -16.2
  },
  "2026-10-13": {
    "vacancy": 308,
    "avg_price": 17878.0,
    "last_vacancy": 306,
    "last_avg_price": 18103.0,
    "vacancy_diff": 2,
    "avg_price_diff": -225.0,
    "my_price": 15000.0,
    "my_vs_avg_pct": -16.1
  },
  "2026-10-14": {
    "vacancy": 307,
    "avg_price": 18354.0,
    "last_vacancy": 306,
    "last_avg_price": 18766.0,
    "vacancy_diff": 1,
    "avg_price_diff": -412.0,
    "my_price": 15600.0,
    "my_vs_avg_pct": -15.0
  },
  "2026-10-15": {
    "vacancy": 303,
    "avg_price": 19232.0,
    "last_vacancy": 302,
    "last_avg_price": 19641.0,
    "vacancy_diff": 1,
    "avg_price_diff": -409.0,
    "my_price": 15600.0,
    "my_vs_avg_pct": -18.9
  },
  "2026-10-16": {
    "vacancy": 304,
    "avg_price": 20487.0,
    "last_vacancy": 303,
    "last_avg_price": 20618.0,
    "vacancy_diff": 1,
    "avg_price_diff": -131.0,
    "my_price": 18000.0,
    "my_vs_avg_pct": -12.1
  },
  "2026-10-17": {
    "vacancy": 293,
    "avg_price": 28392.0,
    "last_vacancy": 292,
    "last_avg_price": 28430.0,
    "vacancy_diff": 1,
    "avg_price_diff": -38.0,
    "my_price": 25000.0,
    "my_vs_avg_pct": -11.9
  },
  "2026-10-18": {
    "vacancy": 306,
    "avg_price": 18429.0,
    "last_vacancy": 305,
    "last_avg_price": 18520.0,
    "vacancy_diff": 1,
    "avg_price_diff": -91.0,
    "my_price": 15000.0,
    "my_vs_avg_pct": -18.6
  },
  "2026-10-19": {
    "vacancy": 306,
    "avg_price": 18241.0,
    "last_vacancy": 305,
    "last_avg_price": 18414.0,
    "vacancy_diff": 1,
    "avg_price_diff": -173.0,
    "my_price": 15000.0,
    "my_vs_avg_pct": -17.8
  },
  "2026-10-20": {
    "vacancy": 305,
    "avg_price": 18611.0,
    "last_vacancy": 304,
    "last_avg_price": 18873.0,
    "vacancy_diff": 1,
    "avg_price_diff": -262.0,
    "my_price": 15000.0,
    "my_vs_avg_pct": -19.4
  },
  "2026-10-21": {
    "vacancy": 306,
    "avg_price": 18803.0,
    "last_vacancy": 305,
    "last_avg_price": 19160.0,
    "vacancy_diff": 1,
    "avg_price_diff": -357.0,
    "my_price": 15600.0,
    "my_vs_avg_pct": -17.0
  },
  "2026-10-22": {
    "vacancy": 305,
    "avg_price": 18801.0,
    "last_vacancy": 304,
    "last_avg_price": 19138.0,
    "vacancy_diff": 1,
    "avg_price_diff": -337.0,
    "my_price": 15600.0,
    "my_vs_avg_pct": -17.0
  },
  "2026-10-23": {
    "vacancy": 307,
    "avg_price": 20483.0,
    "last_vacancy": 306,
    "last_avg_price": 20688.0,
    "vacancy_diff": 1,
    "avg_price_diff": -205.0,
    "my_price": 18000.0,
    "my_vs_avg_pct": -12.1
  },
  "2026-10-24": {
    "vacancy": 293,
    "avg_price": 28613.0,
    "last_vacancy": 292,
    "last_avg_price": 28760.0,
    "vacancy_diff": 1,
    "avg_price_diff": -147.0,
    "my_price": 25600.0,
    "my_vs_avg_pct": -10.5
  },
  "2026-10-25": {
    "vacancy": 308,
    "avg_price": 18491.0,
    "last_vacancy": 306,
    "last_avg_price": 18689.0,
    "vacancy_diff": 2,
    "avg_price_diff": -198.0,
    "my_price": 15000.0,
    "my_vs_avg_pct": -18.9
  },
  "2026-10-26": {
    "vacancy": 307,
    "avg_price": 17811.0,
    "last_vacancy": 306,
    "last_avg_price": 18111.0,
    "vacancy_diff": 1,
    "avg_price_diff": -300.0,
    "my_price": 15000.0,
    "my_vs_avg_pct": -15.8
  },
  "2026-10-27": {
    "vacancy": 308,
    "avg_price": 18527.0,
    "last_vacancy": 307,
    "last_avg_price": 18828.0,
    "vacancy_diff": 1,
    "avg_price_diff": -301.0,
    "my_price": 15000.0,
    "my_vs_avg_pct": -19.0
  },
  "2026-10-28": {
    "vacancy": 309,
    "avg_price": 18371.0,
    "last_vacancy": 308,
    "last_avg_price": 18819.0,
    "vacancy_diff": 1,
    "avg_price_diff": -448.0,
    "my_price": 15600.0,
    "my_vs_avg_pct": -15.1
  },
  "2026-10-29": {
    "vacancy": 310,
    "avg_price": 18697.0,
    "last_vacancy": 309,
    "last_avg_price": 19155.0,
    "vacancy_diff": 1,
    "avg_price_diff": -458.0,
    "my_price": 15600.0,
    "my_vs_avg_pct": -16.6
  },
  "2026-10-30": {
    "vacancy": 309,
    "avg_price": 19924.0,
    "last_vacancy": 308,
    "last_avg_price": 19964.0,
    "vacancy_diff": 1,
    "avg_price_diff": -40.0,
    "my_price": 18000.0,
    "my_vs_avg_pct": -9.7
  },
  "2026-10-31": {
    "vacancy": 305,
    "avg_price": 27381.0,
    "last_vacancy": 304,
    "last_avg_price": 27364.0,
    "vacancy_diff": 1,
    "avg_price_diff": 17.0,
    "my_price": 25000.0,
    "my_vs_avg_pct": -8.7
  },
  "2026-11-01": {
    "vacancy": 299,
    "avg_price": 18961.0,
    "last_vacancy": 298,
    "last_avg_price": 19152.0,
    "vacancy_diff": 1,
    "avg_price_diff": -191.0,
    "my_price": 15000.0,
    "my_vs_avg_pct": -20.9
  },
  "2026-11-02": {
    "vacancy": 297,
    "avg_price": 18989.0,
    "last_vacancy": 296,
    "last_avg_price": 19245.0,
    "vacancy_diff": 1,
    "avg_price_diff": -256.0,
    "my_price": 15000.0,
    "my_vs_avg_pct": -21.0
  },
  "2026-11-03": {
    "vacancy": 299,
    "avg_price": 18024.0,
    "last_vacancy": 298,
    "last_avg_price": 18246.0,
    "vacancy_diff": 1,
    "avg_price_diff": -222.0,
    "my_price": 15000.0,
    "my_vs_avg_pct": -16.8
  },
  "2026-11-04": {
    "vacancy": 296,
    "avg_price": 17988.0,
    "last_vacancy": 295,
    "last_avg_price": 18418.0,
    "vacancy_diff": 1,
    "avg_price_diff": -430.0,
    "my_price": 15600.0,
    "my_vs_avg_pct": -13.3
  },
  "2026-11-05": {
    "vacancy": 296,
    "avg_price": 18283.0,
    "last_vacancy": 295,
    "last_avg_price": 18737.0,
    "vacancy_diff": 1,
    "avg_price_diff": -454.0,
    "my_price": 15600.0,
    "my_vs_avg_pct": -14.7
  },
  "2026-11-06": {
    "vacancy": 292,
    "avg_price": 20252.0,
    "last_vacancy": 291,
    "last_avg_price": 20416.0,
    "vacancy_diff": 1,
    "avg_price_diff": -164.0,
    "my_price": 18000.0,
    "my_vs_avg_pct": -11.1
  },
  "2026-11-07": {
    "vacancy": 239,
    "avg_price": 33220.0,
    "last_vacancy": 238,
    "last_avg_price": 33169.0,
    "vacancy_diff": 1,
    "avg_price_diff": 51.0,
    "my_price": 28800.0,
    "my_vs_avg_pct": -13.3
  },
  "2026-11-08": {
    "vacancy": 280,
    "avg_price": 20680.0,
    "last_vacancy": 278,
    "last_avg_price": 20499.0,
    "vacancy_diff": 2,
    "avg_price_diff": 181.0,
    "my_price": 23800.0,
    "my_vs_avg_pct": 15.1
  },
  "2026-11-09": {
    "vacancy": 297,
    "avg_price": 17768.0,
    "last_vacancy": 295,
    "last_avg_price": 18034.0,
    "vacancy_diff": 2,
    "avg_price_diff": -266.0,
    "my_price": 15000.0,
    "my_vs_avg_pct": -15.6
  },
  "2026-11-10": {
    "vacancy": 297,
    "avg_price": 17985.0,
    "last_vacancy": 295,
    "last_avg_price": 18432.0,
    "vacancy_diff": 2,
    "avg_price_diff": -447.0,
    "my_price": 15000.0,
    "my_vs_avg_pct": -16.6
  },
  "2026-11-11": {
    "vacancy": 295,
    "avg_price": 18177.0,
    "last_vacancy": 293,
    "last_avg_price": 18622.0,
    "vacancy_diff": 2,
    "avg_price_diff": -445.0,
    "my_price": 15600.0,
    "my_vs_avg_pct": -14.2
  },
  "2026-11-12": {
    "vacancy": 296,
    "avg_price": 18996.0,
    "last_vacancy": 294,
    "last_avg_price": 19484.0,
    "vacancy_diff": 2,
    "avg_price_diff": -488.0,
    "my_price": 15600.0,
    "my_vs_avg_pct": -17.9
  },
  "2026-11-13": {
    "vacancy": 298,
    "avg_price": 20114.0,
    "last_vacancy": 296,
    "last_avg_price": 20465.0,
    "vacancy_diff": 2,
    "avg_price_diff": -351.0,
    "my_price": 18000.0,
    "my_vs_avg_pct": -10.5
  },
  "2026-11-14": {
    "vacancy": 274,
    "avg_price": 31258.0,
    "last_vacancy": 273,
    "last_avg_price": 30743.0,
    "vacancy_diff": 1,
    "avg_price_diff": 515.0,
    "my_price": 28800.0,
    "my_vs_avg_pct": -7.9
  },
  "2026-11-15": {
    "vacancy": 299,
    "avg_price": 18659.0,
    "last_vacancy": 297,
    "last_avg_price": 18839.0,
    "vacancy_diff": 2,
    "avg_price_diff": -180.0,
    "my_price": 19800.0,
    "my_vs_avg_pct": 6.1
  },
  "2026-11-16": {
    "vacancy": 298,
    "avg_price": 17898.0,
    "last_vacancy": 296,
    "last_avg_price": 18167.0,
    "vacancy_diff": 2,
    "avg_price_diff": -269.0,
    "my_price": 15000.0,
    "my_vs_avg_pct": -16.2
  },
  "2026-11-17": {
    "vacancy": 298,
    "avg_price": 18028.0,
    "last_vacancy": 296,
    "last_avg_price": 18276.0,
    "vacancy_diff": 2,
    "avg_price_diff": -248.0,
    "my_price": 15000.0,
    "my_vs_avg_pct": -16.8
  },
  "2026-11-18": {
    "vacancy": 299,
    "avg_price": 18365.0,
    "last_vacancy": 298,
    "last_avg_price": 18652.0,
    "vacancy_diff": 1,
    "avg_price_diff": -287.0,
    "my_price": 15600.0,
    "my_vs_avg_pct": -15.1
  },
  "2026-11-19": {
    "vacancy": 299,
    "avg_price": 18997.0,
    "last_vacancy": 298,
    "last_avg_price": 19428.0,
    "vacancy_diff": 1,
    "avg_price_diff": -431.0,
    "my_price": 15600.0,
    "my_vs_avg_pct": -17.9
  },
  "2026-11-20": {
    "vacancy": 287,
    "avg_price": 23345.0,
    "last_vacancy": 286,
    "last_avg_price": 23224.0,
    "vacancy_diff": 1,
    "avg_price_diff": 121.0,
    "my_price": 24400.0,
    "my_vs_avg_pct": 4.5
  },
  "2026-11-21": {
    "vacancy": 271,
    "avg_price": 33303.0,
    "last_vacancy": 271,
    "last_avg_price": 32911.0,
    "vacancy_diff": 0,
    "avg_price_diff": 392.0,
    "my_price": 28800.0,
    "my_vs_avg_pct": -13.5
  },
  "2026-11-22": {
    "vacancy": 288,
    "avg_price": 28005.0,
    "last_vacancy": 286,
    "last_avg_price": 28301.0,
    "vacancy_diff": 2,
    "avg_price_diff": -296.0,
    "my_price": 24400.0,
    "my_vs_avg_pct": -12.9
  },
  "2026-11-23": {
    "vacancy": 296,
    "avg_price": 18264.0,
    "last_vacancy": 296,
    "last_avg_price": 18480.0,
    "vacancy_diff": 0,
    "avg_price_diff": -216.0,
    "my_price": 15000.0,
    "my_vs_avg_pct": -17.9
  },
  "2026-11-24": {
    "vacancy": 297,
    "avg_price": 18013.0,
    "last_vacancy": 296,
    "last_avg_price": 18275.0,
    "vacancy_diff": 1,
    "avg_price_diff": -262.0,
    "my_price": 15000.0,
    "my_vs_avg_pct": -16.7
  },
  "2026-11-25": {
    "vacancy": 297,
    "avg_price": 18373.0,
    "last_vacancy": 296,
    "last_avg_price": 18854.0,
    "vacancy_diff": 1,
    "avg_price_diff": -481.0,
    "my_price": 15600.0,
    "my_vs_avg_pct": -15.1
  },
  "2026-11-26": {
    "vacancy": 295,
    "avg_price": 18773.0,
    "last_vacancy": 294,
    "last_avg_price": 19235.0,
    "vacancy_diff": 1,
    "avg_price_diff": -462.0,
    "my_price": 15600.0,
    "my_vs_avg_pct": -16.9
  },
  "2026-11-27": {
    "vacancy": 295,
    "avg_price": 21233.0,
    "last_vacancy": 294,
    "last_avg_price": 21377.0,
    "vacancy_diff": 1,
    "avg_price_diff": -144.0,
    "my_price": 23200.0,
    "my_vs_avg_pct": 9.3
  },
  "2026-11-28": {
    "vacancy": 281,
    "avg_price": 28828.0,
    "last_vacancy": 283,
    "last_avg_price": 28927.0,
    "vacancy_diff": -2,
    "avg_price_diff": -99.0,
    "my_price": 28800.0,
    "my_vs_avg_pct": -0.1
  },
  "2026-11-29": {
    "vacancy": 297,
    "avg_price": 18230.0,
    "last_vacancy": 296,
    "last_avg_price": 18583.0,
    "vacancy_diff": 1,
    "avg_price_diff": -353.0,
    "my_price": 20400.0,
    "my_vs_avg_pct": 11.9
  },
  "2026-11-30": {
    "vacancy": 301,
    "avg_price": 17838.0,
    "last_vacancy": 300,
    "last_avg_price": 18086.0,
    "vacancy_diff": 1,
    "avg_price_diff": -248.0,
    "my_price": 15000.0,
    "my_vs_avg_pct": -15.9
  },
  "2026-12-01": {
    "vacancy": 275,
    "avg_price": 19037.0,
    "last_vacancy": 274,
    "last_avg_price": 18991.0,
    "vacancy_diff": 1,
    "avg_price_diff": 46.0,
    "my_price": 15000.0,
    "my_vs_avg_pct": -21.2
  },
  "2026-12-02": {
    "vacancy": 275,
    "avg_price": 19028.0,
    "last_vacancy": 273,
    "last_avg_price": 19015.0,
    "vacancy_diff": 2,
    "avg_price_diff": 13.0,
    "my_price": 15600.0,
    "my_vs_avg_pct": -18.0
  },
  "2026-12-03": {
    "vacancy": 274,
    "avg_price": 19574.0,
    "last_vacancy": 272,
    "last_avg_price": 19529.0,
    "vacancy_diff": 2,
    "avg_price_diff": 45.0,
    "my_price": 15600.0,
    "my_vs_avg_pct": -20.3
  },
  "2026-12-04": {
    "vacancy": 276,
    "avg_price": 20779.0,
    "last_vacancy": 274,
    "last_avg_price": 20583.0,
    "vacancy_diff": 2,
    "avg_price_diff": 196.0,
    "my_price": 18000.0,
    "my_vs_avg_pct": -13.4
  },
  "2026-12-05": {
    "vacancy": 266,
    "avg_price": 28544.0,
    "last_vacancy": 265,
    "last_avg_price": 27836.0,
    "vacancy_diff": 1,
    "avg_price_diff": 708.0,
    "my_price": 26200.0,
    "my_vs_avg_pct": -8.2
  },
  "2026-12-06": {
    "vacancy": 275,
    "avg_price": 18842.0,
    "last_vacancy": 274,
    "last_avg_price": 18680.0,
    "vacancy_diff": 1,
    "avg_price_diff": 162.0,
    "my_price": 18000.0,
    "my_vs_avg_pct": -4.5
  },
  "2026-12-07": {
    "vacancy": 275,
    "avg_price": 18460.0,
    "last_vacancy": 274,
    "last_avg_price": 18342.0,
    "vacancy_diff": 1,
    "avg_price_diff": 118.0,
    "my_price": 15000.0,
    "my_vs_avg_pct": -18.7
  },
  "2026-12-08": {
    "vacancy": 275,
    "avg_price": 18774.0,
    "last_vacancy": 274,
    "last_avg_price": 18801.0,
    "vacancy_diff": 1,
    "avg_price_diff": -27.0,
    "my_price": 15000.0,
    "my_vs_avg_pct": -20.1
  },
  "2026-12-09": {
    "vacancy": 277,
    "avg_price": 18843.0,
    "last_vacancy": 276,
    "last_avg_price": 18779.0,
    "vacancy_diff": 1,
    "avg_price_diff": 64.0,
    "my_price": 15600.0,
    "my_vs_avg_pct": -17.2
  },
  "2026-12-10": {
    "vacancy": 273,
    "avg_price": 20631.0,
    "last_vacancy": 256,
    "last_avg_price": 20301.0,
    "vacancy_diff": 17,
    "avg_price_diff": 330.0,
    "my_price": 20400.0,
    "my_vs_avg_pct": -1.1
  },
  "2026-12-11": {
    "vacancy": 262,
    "avg_price": 20715.0,
    "last_vacancy": 261,
    "last_avg_price": 20464.0,
    "vacancy_diff": 1,
    "avg_price_diff": 251.0,
    "my_price": 19200.0,
    "my_vs_avg_pct": -7.3
  },
  "2026-12-12": {
    "vacancy": 250,
    "avg_price": 29117.0,
    "last_vacancy": 248,
    "last_avg_price": 28838.0,
    "vacancy_diff": 2,
    "avg_price_diff": 279.0,
    "my_price": 26200.0,
    "my_vs_avg_pct": -10.0
  },
  "2026-12-13": {
    "vacancy": 259,
    "avg_price": 19997.0,
    "last_vacancy": 258,
    "last_avg_price": 20095.0,
    "vacancy_diff": 1,
    "avg_price_diff": -98.0,
    "my_price": 18000.0,
    "my_vs_avg_pct": -10.0
  },
  "2026-12-14": {
    "vacancy": 262,
    "avg_price": 18489.0,
    "last_vacancy": 259,
    "last_avg_price": 18352.0,
    "vacancy_diff": 3,
    "avg_price_diff": 137.0,
    "my_price": 15000.0,
    "my_vs_avg_pct": -18.9
  },
  "2026-12-15": {
    "vacancy": 260,
    "avg_price": 18716.0,
    "last_vacancy": 259,
    "last_avg_price": 18581.0,
    "vacancy_diff": 1,
    "avg_price_diff": 135.0,
    "my_price": 15000.0,
    "my_vs_avg_pct": -19.9
  },
  "2026-12-16": {
    "vacancy": 260,
    "avg_price": 18882.0,
    "last_vacancy": 259,
    "last_avg_price": 18910.0,
    "vacancy_diff": 1,
    "avg_price_diff": -28.0,
    "my_price": 15600.0,
    "my_vs_avg_pct": -17.4
  },
  "2026-12-17": {
    "vacancy": 259,
    "avg_price": 18932.0,
    "last_vacancy": 257,
    "last_avg_price": 18885.0,
    "vacancy_diff": 2,
    "avg_price_diff": 47.0,
    "my_price": 15600.0,
    "my_vs_avg_pct": -17.6
  },
  "2026-12-18": {
    "vacancy": 258,
    "avg_price": 20454.0,
    "last_vacancy": 257,
    "last_avg_price": 20135.0,
    "vacancy_diff": 1,
    "avg_price_diff": 319.0,
    "my_price": 19200.0,
    "my_vs_avg_pct": -6.1
  },
  "2026-12-19": {
    "vacancy": 252,
    "avg_price": 27420.0,
    "last_vacancy": 251,
    "last_avg_price": 27081.0,
    "vacancy_diff": 1,
    "avg_price_diff": 339.0,
    "my_price": 24400.0,
    "my_vs_avg_pct": -11.0
  },
  "2026-12-20": {
    "vacancy": 255,
    "avg_price": 19571.0,
    "last_vacancy": 254,
    "last_avg_price": 19358.0,
    "vacancy_diff": 1,
    "avg_price_diff": 213.0,
    "my_price": 15600.0,
    "my_vs_avg_pct": -20.3
  },
  "2026-12-21": {
    "vacancy": 255,
    "avg_price": 19629.0,
    "last_vacancy": 254,
    "last_avg_price": 19455.0,
    "vacancy_diff": 1,
    "avg_price_diff": 174.0,
    "my_price": 15600.0,
    "my_vs_avg_pct": -20.5
  },
  "2026-12-22": {
    "vacancy": 254,
    "avg_price": 19941.0,
    "last_vacancy": 253,
    "last_avg_price": 19761.0,
    "vacancy_diff": 1,
    "avg_price_diff": 180.0,
    "my_price": 15600.0,
    "my_vs_avg_pct": -21.8
  },
  "2026-12-23": {
    "vacancy": 255,
    "avg_price": 20242.0,
    "last_vacancy": 254,
    "last_avg_price": 20131.0,
    "vacancy_diff": 1,
    "avg_price_diff": 111.0,
    "my_price": 20400.0,
    "my_vs_avg_pct": 0.8
  },
  "2026-12-24": {
    "vacancy": 255,
    "avg_price": 21620.0,
    "last_vacancy": 254,
    "last_avg_price": 21334.0,
    "vacancy_diff": 1,
    "avg_price_diff": 286.0,
    "my_price": 23800.0,
    "my_vs_avg_pct": 10.1
  },
  "2026-12-25": {
    "vacancy": 257,
    "avg_price": 23181.0,
    "last_vacancy": 256,
    "last_avg_price": 22827.0,
    "vacancy_diff": 1,
    "avg_price_diff": 354.0,
    "my_price": 23800.0,
    "my_vs_avg_pct": 2.7
  },
  "2026-12-26": {
    "vacancy": 247,
    "avg_price": 29407.0,
    "last_vacancy": 246,
    "last_avg_price": 28751.0,
    "vacancy_diff": 1,
    "avg_price_diff": 656.0,
    "my_price": 26200.0,
    "my_vs_avg_pct": -10.9
  },
  "2026-12-27": {
    "vacancy": 252,
    "avg_price": 25308.0,
    "last_vacancy": 251,
    "last_avg_price": 24528.0,
    "vacancy_diff": 1,
    "avg_price_diff": 780.0,
    "my_price": 22800.0,
    "my_vs_avg_pct": -9.9
  },
  "2026-12-28": {
    "vacancy": 252,
    "avg_price": 26005.0,
    "last_vacancy": 251,
    "last_avg_price": 24748.0,
    "vacancy_diff": 1,
    "avg_price_diff": 1257.0,
    "my_price": 22800.0,
    "my_vs_avg_pct": -12.3
  },
  "2026-12-29": {
    "vacancy": 250,
    "avg_price": 26446.0,
    "last_vacancy": 249,
    "last_avg_price": 25774.0,
    "vacancy_diff": 1,
    "avg_price_diff": 672.0,
    "my_price": 23800.0,
    "my_vs_avg_pct": -10.0
  },
  "2026-12-30": {
    "vacancy": 250,
    "avg_price": 27641.0,
    "last_vacancy": 249,
    "last_avg_price": 26546.0,
    "vacancy_diff": 1,
    "avg_price_diff": 1095.0,
    "my_price": 26200.0,
    "my_vs_avg_pct": -5.2
  },
  "2026-12-31": {
    "vacancy": 241,
    "avg_price": 34299.0,
    "last_vacancy": 240,
    "last_avg_price": 33328.0,
    "vacancy_diff": 1,
    "avg_price_diff": 971.0,
    "my_price": 28800.0,
    "my_vs_avg_pct": -16.0
  },
  "2027-01-01": {
    "vacancy": 202,
    "avg_price": 33412.0,
    "last_vacancy": 202,
    "last_avg_price": 33503.0,
    "vacancy_diff": 0,
    "avg_price_diff": -91.0,
    "my_price": 27400.0,
    "my_vs_avg_pct": -18.0
  },
  "2027-01-02": {
    "vacancy": 204,
    "avg_price": 31120.0,
    "last_vacancy": 204,
    "last_avg_price": 31156.0,
    "vacancy_diff": 0,
    "avg_price_diff": -36.0,
    "my_price": 23800.0,
    "my_vs_avg_pct": -23.5
  },
  "2027-01-03": {
    "vacancy": 209,
    "avg_price": 23121.0,
    "last_vacancy": 209,
    "last_avg_price": 23139.0,
    "vacancy_diff": 0,
    "avg_price_diff": -18.0,
    "my_price": 16600.0,
    "my_vs_avg_pct": -28.2
  },
  "2027-01-04": {
    "vacancy": 208,
    "avg_price": 21578.0,
    "last_vacancy": 207,
    "last_avg_price": 21276.0,
    "vacancy_diff": 1,
    "avg_price_diff": 302.0,
    "my_price": 16000.0,
    "my_vs_avg_pct": -25.9
  },
  "2027-01-05": {
    "vacancy": 207,
    "avg_price": 21447.0,
    "last_vacancy": 206,
    "last_avg_price": 21102.0,
    "vacancy_diff": 1,
    "avg_price_diff": 345.0,
    "my_price": 16000.0,
    "my_vs_avg_pct": -25.4
  },
  "2027-01-06": {
    "vacancy": 207,
    "avg_price": 21205.0,
    "last_vacancy": 206,
    "last_avg_price": 20935.0,
    "vacancy_diff": 1,
    "avg_price_diff": 270.0,
    "my_price": 16000.0,
    "my_vs_avg_pct": -24.5
  },
  "2027-01-07": {
    "vacancy": 207,
    "avg_price": 21126.0,
    "last_vacancy": 206,
    "last_avg_price": 20912.0,
    "vacancy_diff": 1,
    "avg_price_diff": 214.0,
    "my_price": 16000.0,
    "my_vs_avg_pct": -24.3
  },
  "2027-01-08": {
    "vacancy": 207,
    "avg_price": 21794.0,
    "last_vacancy": 206,
    "last_avg_price": 21440.0,
    "vacancy_diff": 1,
    "avg_price_diff": 354.0,
    "my_price": 17800.0,
    "my_vs_avg_pct": -18.3
  },
  "2027-01-09": {
    "vacancy": 204,
    "avg_price": 28218.0,
    "last_vacancy": 203,
    "last_avg_price": 28359.0,
    "vacancy_diff": 1,
    "avg_price_diff": -141.0,
    "my_price": 25600.0,
    "my_vs_avg_pct": -9.3
  },
  "2027-01-10": {
    "vacancy": 204,
    "avg_price": 26429.0,
    "last_vacancy": 203,
    "last_avg_price": 26468.0,
    "vacancy_diff": 1,
    "avg_price_diff": -39.0,
    "my_price": 23800.0,
    "my_vs_avg_pct": -9.9
  },
  "2027-01-11": {
    "vacancy": 207,
    "avg_price": 21405.0,
    "last_vacancy": 206,
    "last_avg_price": 21391.0,
    "vacancy_diff": 1,
    "avg_price_diff": 14.0,
    "my_price": 16000.0,
    "my_vs_avg_pct": -25.3
  },
  "2027-01-12": {
    "vacancy": 206,
    "avg_price": 20901.0,
    "last_vacancy": 205,
    "last_avg_price": 20694.0,
    "vacancy_diff": 1,
    "avg_price_diff": 207.0,
    "my_price": 16000.0,
    "my_vs_avg_pct": -23.4
  },
  "2027-01-13": {
    "vacancy": 207,
    "avg_price": 21150.0,
    "last_vacancy": 206,
    "last_avg_price": 20972.0,
    "vacancy_diff": 1,
    "avg_price_diff": 178.0,
    "my_price": 16600.0,
    "my_vs_avg_pct": -21.5
  },
  "2027-01-14": {
    "vacancy": 207,
    "avg_price": 21344.0,
    "last_vacancy": 206,
    "last_avg_price": 21197.0,
    "vacancy_diff": 1,
    "avg_price_diff": 147.0,
    "my_price": 16600.0,
    "my_vs_avg_pct": -22.2
  },
  "2027-01-15": {
    "vacancy": 207,
    "avg_price": 22151.0,
    "last_vacancy": 206,
    "last_avg_price": 21856.0,
    "vacancy_diff": 1,
    "avg_price_diff": 295.0,
    "my_price": 19000.0,
    "my_vs_avg_pct": -14.2
  },
  "2027-01-16": {
    "vacancy": 202,
    "avg_price": 27777.0,
    "last_vacancy": 202,
    "last_avg_price": 27836.0,
    "vacancy_diff": 0,
    "avg_price_diff": -59.0,
    "my_price": 25600.0,
    "my_vs_avg_pct": -7.8
  },
  "2027-01-17": {
    "vacancy": 208,
    "avg_price": 20920.0,
    "last_vacancy": 207,
    "last_avg_price": 20919.0,
    "vacancy_diff": 1,
    "avg_price_diff": 1.0,
    "my_price": 16000.0,
    "my_vs_avg_pct": -23.5
  },
  "2027-01-18": {
    "vacancy": 206,
    "avg_price": 20788.0,
    "last_vacancy": 205,
    "last_avg_price": 20856.0,
    "vacancy_diff": 1,
    "avg_price_diff": -68.0,
    "my_price": 16000.0,
    "my_vs_avg_pct": -23.0
  },
  "2027-01-19": {
    "vacancy": 207,
    "avg_price": 21040.0,
    "last_vacancy": 207,
    "last_avg_price": 20931.0,
    "vacancy_diff": 0,
    "avg_price_diff": 109.0,
    "my_price": 16000.0,
    "my_vs_avg_pct": -24.0
  },
  "2027-01-20": {
    "vacancy": 207,
    "avg_price": 21144.0,
    "last_vacancy": 207,
    "last_avg_price": 21025.0,
    "vacancy_diff": 0,
    "avg_price_diff": 119.0,
    "my_price": 16600.0,
    "my_vs_avg_pct": -21.5
  },
  "2027-01-21": {
    "vacancy": 207,
    "avg_price": 20992.0,
    "last_vacancy": 206,
    "last_avg_price": 20825.0,
    "vacancy_diff": 1,
    "avg_price_diff": 167.0,
    "my_price": 16600.0,
    "my_vs_avg_pct": -20.9
  },
  "2027-01-22": {
    "vacancy": 207,
    "avg_price": 22161.0,
    "last_vacancy": 207,
    "last_avg_price": 21886.0,
    "vacancy_diff": 0,
    "avg_price_diff": 275.0,
    "my_price": 19000.0,
    "my_vs_avg_pct": -14.3
  },
  "2027-01-23": {
    "vacancy": 201,
    "avg_price": 28218.0,
    "last_vacancy": 201,
    "last_avg_price": 28262.0,
    "vacancy_diff": 0,
    "avg_price_diff": -44.0,
    "my_price": 27400.0,
    "my_vs_avg_pct": -2.9
  },
  "2027-01-24": {
    "vacancy": 208,
    "avg_price": 21089.0,
    "last_vacancy": 207,
    "last_avg_price": 21123.0,
    "vacancy_diff": 1,
    "avg_price_diff": -34.0,
    "my_price": 16000.0,
    "my_vs_avg_pct": -24.1
  },
  "2027-01-25": {
    "vacancy": 208,
    "avg_price": 20818.0,
    "last_vacancy": 207,
    "last_avg_price": 20688.0,
    "vacancy_diff": 1,
    "avg_price_diff": 130.0,
    "my_price": 16000.0,
    "my_vs_avg_pct": -23.1
  },
  "2027-01-26": {
    "vacancy": 208,
    "avg_price": 20934.0,
    "last_vacancy": 207,
    "last_avg_price": 20802.0,
    "vacancy_diff": 1,
    "avg_price_diff": 132.0,
    "my_price": 16000.0,
    "my_vs_avg_pct": -23.6
  },
  "2027-01-27": {
    "vacancy": 208,
    "avg_price": 20904.0,
    "last_vacancy": 207,
    "last_avg_price": 20781.0,
    "vacancy_diff": 1,
    "avg_price_diff": 123.0,
    "my_price": 16600.0,
    "my_vs_avg_pct": -20.6
  },
  "2027-01-28": {
    "vacancy": 208,
    "avg_price": 20975.0,
    "last_vacancy": 207,
    "last_avg_price": 20857.0,
    "vacancy_diff": 1,
    "avg_price_diff": 118.0,
    "my_price": 16600.0,
    "my_vs_avg_pct": -20.9
  },
  "2027-01-29": {
    "vacancy": 208,
    "avg_price": 22195.0,
    "last_vacancy": 207,
    "last_avg_price": 21886.0,
    "vacancy_diff": 1,
    "avg_price_diff": 309.0,
    "my_price": 17800.0,
    "my_vs_avg_pct": -19.8
  },
  "2027-01-30": {
    "vacancy": 204,
    "avg_price": 27626.0,
    "last_vacancy": 203,
    "last_avg_price": 27660.0,
    "vacancy_diff": 1,
    "avg_price_diff": -34.0,
    "my_price": 25600.0,
    "my_vs_avg_pct": -7.3
  },
  "2027-01-31": {
    "vacancy": 208,
    "avg_price": 20985.0,
    "last_vacancy": 207,
    "last_avg_price": 20993.0,
    "vacancy_diff": 1,
    "avg_price_diff": -8.0,
    "my_price": 16000.0,
    "my_vs_avg_pct": -23.8
  },
  "2027-02-01": {
    "vacancy": 188,
    "avg_price": 20696.0,
    "last_vacancy": 188,
    "last_avg_price": 20719.0,
    "vacancy_diff": 0,
    "avg_price_diff": -23.0,
    "my_price": 16000.0,
    "my_vs_avg_pct": -22.7
  },
  "2027-02-02": {
    "vacancy": 188,
    "avg_price": 20832.0,
    "last_vacancy": 188,
    "last_avg_price": 20856.0,
    "vacancy_diff": 0,
    "avg_price_diff": -24.0,
    "my_price": 16000.0,
    "my_vs_avg_pct": -23.2
  },
  "2027-02-03": {
    "vacancy": 188,
    "avg_price": 20895.0,
    "last_vacancy": 188,
    "last_avg_price": 20912.0,
    "vacancy_diff": 0,
    "avg_price_diff": -17.0,
    "my_price": 16600.0,
    "my_vs_avg_pct": -20.6
  },
  "2027-02-04": {
    "vacancy": 188,
    "avg_price": 21328.0,
    "last_vacancy": 188,
    "last_avg_price": 21326.0,
    "vacancy_diff": 0,
    "avg_price_diff": 2.0,
    "my_price": 16600.0,
    "my_vs_avg_pct": -22.2
  },
  "2027-02-05": {
    "vacancy": 188,
    "avg_price": 23608.0,
    "last_vacancy": 188,
    "last_avg_price": 23544.0,
    "vacancy_diff": 0,
    "avg_price_diff": 64.0,
    "my_price": 19000.0,
    "my_vs_avg_pct": -19.5
  },
  "2027-02-06": {
    "vacancy": 185,
    "avg_price": 29337.0,
    "last_vacancy": 185,
    "last_avg_price": 29652.0,
    "vacancy_diff": 0,
    "avg_price_diff": -315.0,
    "my_price": 27400.0,
    "my_vs_avg_pct": -6.6
  },
  "2027-02-07": {
    "vacancy": 186,
    "avg_price": 22857.0,
    "last_vacancy": 186,
    "last_avg_price": 23046.0,
    "vacancy_diff": 0,
    "avg_price_diff": -189.0,
    "my_price": 17800.0,
    "my_vs_avg_pct": -22.1
  },
  "2027-02-08": {
    "vacancy": 187,
    "avg_price": 22903.0,
    "last_vacancy": 187,
    "last_avg_price": 22990.0,
    "vacancy_diff": 0,
    "avg_price_diff": -87.0,
    "my_price": 17800.0,
    "my_vs_avg_pct": -22.3
  },
  "2027-02-09": {
    "vacancy": 187,
    "avg_price": 22903.0,
    "last_vacancy": 187,
    "last_avg_price": 22946.0,
    "vacancy_diff": 0,
    "avg_price_diff": -43.0,
    "my_price": 17800.0,
    "my_vs_avg_pct": -22.3
  },
  "2027-02-10": {
    "vacancy": 187,
    "avg_price": 23188.0,
    "last_vacancy": 187,
    "last_avg_price": 23167.0,
    "vacancy_diff": 0,
    "avg_price_diff": 21.0,
    "my_price": 17800.0,
    "my_vs_avg_pct": -23.2
  },
  "2027-02-11": {
    "vacancy": 186,
    "avg_price": 22641.0,
    "last_vacancy": 186,
    "last_avg_price": 22774.0,
    "vacancy_diff": 0,
    "avg_price_diff": -133.0,
    "my_price": 19000.0,
    "my_vs_avg_pct": -16.1
  },
  "2027-02-12": {
    "vacancy": 188,
    "avg_price": 23327.0,
    "last_vacancy": 188,
    "last_avg_price": 23264.0,
    "vacancy_diff": 0,
    "avg_price_diff": 63.0,
    "my_price": 19000.0,
    "my_vs_avg_pct": -18.5
  },
  "2027-02-13": {
    "vacancy": 183,
    "avg_price": 29413.0,
    "last_vacancy": 183,
    "last_avg_price": 29374.0,
    "vacancy_diff": 0,
    "avg_price_diff": 39.0,
    "my_price": 26800.0,
    "my_vs_avg_pct": -8.9
  },
  "2027-02-14": {
    "vacancy": 188,
    "avg_price": 21127.0,
    "last_vacancy": 188,
    "last_avg_price": 21324.0,
    "vacancy_diff": 0,
    "avg_price_diff": -197.0,
    "my_price": 16000.0,
    "my_vs_avg_pct": -24.3
  },
  "2027-02-15": {
    "vacancy": 188,
    "avg_price": 20897.0,
    "last_vacancy": 188,
    "last_avg_price": 20939.0,
    "vacancy_diff": 0,
    "avg_price_diff": -42.0,
    "my_price": 16000.0,
    "my_vs_avg_pct": -23.4
  },
  "2027-02-16": {
    "vacancy": 188,
    "avg_price": 21030.0,
    "last_vacancy": 188,
    "last_avg_price": 21072.0,
    "vacancy_diff": 0,
    "avg_price_diff": -42.0,
    "my_price": 16000.0,
    "my_vs_avg_pct": -23.9
  },
  "2027-02-17": {
    "vacancy": 188,
    "avg_price": 21073.0,
    "last_vacancy": 188,
    "last_avg_price": 21111.0,
    "vacancy_diff": 0,
    "avg_price_diff": -38.0,
    "my_price": 16600.0,
    "my_vs_avg_pct": -21.2
  },
  "2027-02-18": {
    "vacancy": 188,
    "avg_price": 21218.0,
    "last_vacancy": 188,
    "last_avg_price": 21257.0,
    "vacancy_diff": 0,
    "avg_price_diff": -39.0,
    "my_price": 16600.0,
    "my_vs_avg_pct": -21.8
  },
  "2027-02-19": {
    "vacancy": 187,
    "avg_price": 22486.0,
    "last_vacancy": 187,
    "last_avg_price": 22449.0,
    "vacancy_diff": 0,
    "avg_price_diff": 37.0,
    "my_price": 19000.0,
    "my_vs_avg_pct": -15.5
  },
  "2027-02-20": {
    "vacancy": 183,
    "avg_price": 28431.0,
    "last_vacancy": 183,
    "last_avg_price": 28796.0,
    "vacancy_diff": 0,
    "avg_price_diff": -365.0,
    "my_price": 25600.0,
    "my_vs_avg_pct": -10.0
  },
  "2027-02-21": {
    "vacancy": 187,
    "avg_price": 21353.0,
    "last_vacancy": 187,
    "last_avg_price": 21575.0,
    "vacancy_diff": 0,
    "avg_price_diff": -222.0,
    "my_price": 16000.0,
    "my_vs_avg_pct": -25.1
  },
  "2027-02-22": {
    "vacancy": 187,
    "avg_price": 21568.0,
    "last_vacancy": 187,
    "last_avg_price": 21613.0,
    "vacancy_diff": 0,
    "avg_price_diff": -45.0,
    "my_price": 16000.0,
    "my_vs_avg_pct": -25.8
  },
  "2027-02-23": {
    "vacancy": 187,
    "avg_price": 21143.0,
    "last_vacancy": 187,
    "last_avg_price": 21406.0,
    "vacancy_diff": 0,
    "avg_price_diff": -263.0,
    "my_price": 16000.0,
    "my_vs_avg_pct": -24.3
  },
  "2027-02-24": {
    "vacancy": 186,
    "avg_price": 21038.0,
    "last_vacancy": 186,
    "last_avg_price": 21094.0,
    "vacancy_diff": 0,
    "avg_price_diff": -56.0,
    "my_price": 16600.0,
    "my_vs_avg_pct": -21.1
  },
  "2027-02-25": {
    "vacancy": 187,
    "avg_price": 20793.0,
    "last_vacancy": 187,
    "last_avg_price": 20845.0,
    "vacancy_diff": 0,
    "avg_price_diff": -52.0,
    "my_price": 16600.0,
    "my_vs_avg_pct": -20.2
  },
  "2027-02-26": {
    "vacancy": 187,
    "avg_price": 21861.0,
    "last_vacancy": 187,
    "last_avg_price": 21827.0,
    "vacancy_diff": 0,
    "avg_price_diff": 34.0,
    "my_price": 19000.0,
    "my_vs_avg_pct": -13.1
  },
  "2027-02-27": {
    "vacancy": 183,
    "avg_price": 27756.0,
    "last_vacancy": 183,
    "last_avg_price": 28059.0,
    "vacancy_diff": 0,
    "avg_price_diff": -303.0,
    "my_price": 25600.0,
    "my_vs_avg_pct": -7.8
  },
  "2027-02-28": {
    "vacancy": 188,
    "avg_price": 20846.0,
    "last_vacancy": 188,
    "last_avg_price": 21040.0,
    "vacancy_diff": 0,
    "avg_price_diff": -194.0,
    "my_price": 16000.0,
    "my_vs_avg_pct": -23.2
  }
}